{
  "subset": "today",
  "generated_at": "2026-06-18T06:00:02.032001+02:00",
  "event_count": 16,
  "disclaimer": "Die auf rausgucken.de angezeigten Veranstaltungsinformationen werden automatisch von öffentlich zugänglichen Webseiten gesammelt. Trotz größtmöglicher Sorgfalt übernehmen wir keine Gewähr für die Richtigkeit, Vollständigkeit oder Aktualität der Daten. Bitte überprüfen Sie alle Angaben auf der jeweiligen Originalseite (siehe original_url jedes Eintrags) bevor Sie teilnehmen.",
  "events": [
    {
      "id": "81c3d0780fca5b88",
      "title": "Zwergeninsel in Schlösslesfeld",
      "date_start": "2026-06-18",
      "date_end": null,
      "time": "09:45 - 10:30",
      "description": "In Schlösslesfeld bietet sich die Zwergeninsel an, um Kniereiter und Singspiele zu genießen. Von 09:45 bis 10:30 Uhr laden alle Einheimischen und Besucher ein, diese besondere Veranstaltung mitzuverfolgen.",
      "location": "Stadtbibliothek Ludwigsburg",
      "price": "Kostenlos",
      "age_min": null,
      "age_max": null,
      "tags": [],
      "link": "https://events-stabi.ludwigsburg.de/Veranstaltung/cmx68f8aee4350bb.html",
      "original_url": "https://events-stabi.ludwigsburg.de/Veranstaltung/cmx68f8aee4350bb.html",
      "source": "stabi",
      "city": "ludwigsburg",
      "slug": "zwergeninsel-in-schloesslesfeld-2026-06-18-stab",
      "weekdays": [
        4
      ],
      "scraped_at": "2026-06-17T02:15:12.741714+02:00",
      "extraction_confidence": 1.0,
      "is_new": false,
      "is_booked_out": false,
      "sponsored": false,
      "editorial_tip": null,
      "source_label": "Stadtbibliothek Ludwigsburg",
      "canonical_url": "https://www.rausgucken.de/ludwigsburg/events/zwergeninsel-in-schloesslesfeld-2026-06-18-stab"
    },
    {
      "id": "cb54996b95ae41d9",
      "title": "Zwergeninsel in Schlösslesfeld",
      "date_start": "2026-06-18",
      "date_end": null,
      "time": "09:45 bis 10:30 Uhr",
      "description": "In der Stadtbibliothek Zweigstelle Schlösslesfeld erwartet eine faszinierende Reise durch die Legenden der Zwergeninsel. Mit spannenden Geschichten und interaktiven Elementen bietet dieses literarische Event ein einzigartiges Erlebnis für alle Altersgruppen.",
      "location": "Stadtbibliothek Zweigstelle Schlösslesfeld",
      "price": null,
      "age_min": null,
      "age_max": null,
      "tags": [],
      "link": "https://events-stabi.ludwigsburg.de/Veranstaltung/cmx68f8aee4350bb.html",
      "original_url": "https://events-stabi.ludwigsburg.de/Veranstaltung/cmx68f8aee4350bb.html",
      "source": "ludwigsburg_stadt",
      "city": "ludwigsburg",
      "slug": "zwergeninsel-in-schloesslesfeld-2026-06-18-ludw",
      "weekdays": [
        4
      ],
      "scraped_at": "2026-06-17T02:20:31.480746+02:00",
      "extraction_confidence": 1.0,
      "is_new": false,
      "is_booked_out": false,
      "sponsored": false,
      "editorial_tip": null,
      "source_label": "Stadt Ludwigsburg",
      "canonical_url": "https://www.rausgucken.de/ludwigsburg/events/zwergeninsel-in-schloesslesfeld-2026-06-18-ludw"
    },
    {
      "id": "d311ac3cea4c77f4",
      "title": "Walk&Talk",
      "date_start": "2026-06-18",
      "date_end": null,
      "time": "10:00-11:30 Uhr",
      "description": "In der Bärenwiese, gegenüber dem Eingang Blühendes Barock, findet ein informeller Spaziergang mit fachkundiger Begleitung statt. Themen und Thüringer Geschichte werden lebendig erzählt.",
      "location": "Bärenwiese, gegenüber Eingang Blühendes Barock",
      "price": null,
      "age_min": null,
      "age_max": null,
      "tags": [],
      "link": "https://www.ludwigsburg.de/site/Ludwigsburg-Internet-2020/node/16990284/zmdetail_523255297952/index.html",
      "original_url": "https://www.ludwigsburg.de/site/Ludwigsburg-Internet-2020/node/16990284/zmdetail_523255297952/index.html",
      "source": "ludwigsburg_stadt",
      "city": "ludwigsburg",
      "slug": "walktalk-2026-06-18-ludw",
      "weekdays": [
        4
      ],
      "scraped_at": "2026-06-17T02:20:31.478220+02:00",
      "extraction_confidence": 1.0,
      "is_new": false,
      "is_booked_out": false,
      "sponsored": false,
      "editorial_tip": null,
      "source_label": "Stadt Ludwigsburg",
      "canonical_url": "https://www.rausgucken.de/ludwigsburg/events/walktalk-2026-06-18-ludw"
    },
    {
      "id": "8227c524c1911606",
      "title": "Sport für die Seele",
      "date_start": "2026-06-18",
      "date_end": null,
      "time": "11:10 bis 12:00 Uhr",
      "description": "In diesem Veranstaltungskonzept mischen sich körperliche Aktivität und spirituelle Ruhe. Teilnehmer können im Rahmen von Yoga-Workshops oder Meditationssessions den Geist entspannen, während der Körper gezielt trainiert wird.",
      "location": "MTV Ludwigsburg",
      "price": null,
      "age_min": null,
      "age_max": null,
      "tags": [
        "Sport"
      ],
      "link": "https://mtv-ludwigsburg.de/project/sport-fuer-die-seele/",
      "original_url": "https://mtv-ludwigsburg.de/project/sport-fuer-die-seele/",
      "source": "ludwigsburg_stadt",
      "city": "ludwigsburg",
      "slug": "sport-fuer-die-seele-2026-06-18-ludw",
      "weekdays": [
        4
      ],
      "scraped_at": "2026-06-17T02:20:31.478433+02:00",
      "extraction_confidence": 1.0,
      "is_new": false,
      "is_booked_out": false,
      "sponsored": false,
      "editorial_tip": null,
      "source_label": "Stadt Ludwigsburg",
      "canonical_url": "https://www.rausgucken.de/ludwigsburg/events/sport-fuer-die-seele-2026-06-18-ludw"
    },
    {
      "id": "a57aa16767fb4425",
      "title": "Female Founders Stammtisch - Lunch Edition",
      "date_start": "2026-06-18",
      "date_end": null,
      "time": "12:00 - 14:00",
      "description": "In der Female Founders Stammtisch - Lunch Edition treffen sich Gründerinnen zum Austausch und Networking im gemütlichen Rahmen des Tinkertanks.",
      "location": "Tinkertank",
      "price": null,
      "age_min": null,
      "age_max": null,
      "tags": [],
      "link": "https://tinkertank.de/de/work/gruendungs-werkstatt-female-founders-stammtisch",
      "original_url": "https://tinkertank.de/de/work/gruendungs-werkstatt-female-founders-stammtisch",
      "source": "ludwigsburg_stadt",
      "city": "ludwigsburg",
      "slug": "female-founders-stammtisch---lunch-edition-2026-06-18-ludw",
      "weekdays": [
        4
      ],
      "scraped_at": "2026-06-17T02:20:31.478670+02:00",
      "extraction_confidence": 1.0,
      "is_new": false,
      "is_booked_out": false,
      "sponsored": false,
      "editorial_tip": null,
      "source_label": "Stadt Ludwigsburg",
      "canonical_url": "https://www.rausgucken.de/ludwigsburg/events/female-founders-stammtisch---lunch-edition-2026-06-18-ludw"
    },
    {
      "id": "301b20051b0747de",
      "title": "Gründungswerkstatt",
      "date_start": "2026-06-18",
      "date_end": null,
      "time": "12:00 - 17:00",
      "description": "In dieser Werkstatt lernen Teilnehmer, wie sie ihre Ideen in ein Projekt verwirklichen können. Mit Unterstützung von Fachexperten arbeiten sie an der Gestaltung und Umsetzung ihrer Konzepte im Raum des Tinkertanks.",
      "location": "Tinkertank",
      "price": null,
      "age_min": null,
      "age_max": null,
      "tags": [
        "Workshop"
      ],
      "link": "https://tinkertank.de/de/work/gruendungswerkstatt-termin6",
      "original_url": "https://tinkertank.de/de/work/gruendungswerkstatt-termin6",
      "source": "ludwigsburg_stadt",
      "city": "ludwigsburg",
      "slug": "gruendungswerkstatt-2026-06-18-ludw",
      "weekdays": [
        4
      ],
      "scraped_at": "2026-06-17T02:20:31.478925+02:00",
      "extraction_confidence": 1.0,
      "is_new": false,
      "is_booked_out": false,
      "sponsored": false,
      "editorial_tip": null,
      "source_label": "Stadt Ludwigsburg",
      "canonical_url": "https://www.rausgucken.de/ludwigsburg/events/gruendungswerkstatt-2026-06-18-ludw"
    },
    {
      "id": "d378faf0b7b490b1",
      "title": "Bilderbuchkino am Nachmittag",
      "date_start": "2026-06-18",
      "date_end": "2026-06-18",
      "time": "15:30 - 16:00",
      "description": "In der Kinderbibliothek von Ludwigsburg wird ein Bilderbuchkino am Nachmittag stattfinden. Einige Bilderbücher werden vorgelesen, während die entsprechenden Bilder auf einem großen Bildschirm gezeigt werden. Ideal für Familien mit Kindern ab 4 Jahren und kostenfrei.",
      "location": "Stadtbibliothek Ludwigsburg",
      "price": "Kostenlos",
      "age_min": 4,
      "age_max": null,
      "tags": [
        "Kinder",
        "Familie"
      ],
      "link": "https://events-stabi.ludwigsburg.de/Veranstaltung/cmx695fcfd4968c3.html",
      "original_url": "https://events-stabi.ludwigsburg.de/Veranstaltung/cmx695fcfd4968c3.html",
      "source": "stabi",
      "city": "ludwigsburg",
      "slug": "bilderbuchkino-am-nachmittag-2026-06-18-stab",
      "weekdays": [
        4
      ],
      "scraped_at": "2026-06-17T02:15:03.619552+02:00",
      "extraction_confidence": 1.0,
      "is_new": false,
      "is_booked_out": false,
      "sponsored": false,
      "editorial_tip": null,
      "source_label": "Stadtbibliothek Ludwigsburg",
      "canonical_url": "https://www.rausgucken.de/ludwigsburg/events/bilderbuchkino-am-nachmittag-2026-06-18-stab"
    },
    {
      "id": "f49b23130c5c422f",
      "title": "Gymnastikgruppe für Frauen 55+ sucht neue Teilnehmerinnen",
      "date_start": "2026-06-18",
      "date_end": null,
      "time": "15:30 - 16:30 Uhr",
      "description": "In der Gymnastikgruppe für Frauen ab 55+jährig sind neue Mitstreiterinnen willkommen. Die Gruppe trefft sich regelmäßig an der Begegnungsstätte Stuttgarter Straße 12/1 und kombiniert leichte Übungen mit geselligem Austausch.",
      "location": "Begegnungsstätte Stuttgarter Straße 12/1",
      "price": null,
      "age_min": null,
      "age_max": null,
      "tags": [],
      "link": "https://www.ludwigsburg.de/site/Ludwigsburg-Internet-2020/node/16990284/zmdetail_523254941211/index.html",
      "original_url": "https://www.ludwigsburg.de/site/Ludwigsburg-Internet-2020/node/16990284/zmdetail_523254941211/index.html",
      "source": "ludwigsburg_stadt",
      "city": "ludwigsburg",
      "slug": "gymnastikgruppe-fuer-frauen-55-sucht-neue-teilnehmerinnen-2026-06-18-ludw",
      "weekdays": [
        4
      ],
      "scraped_at": "2026-06-17T02:20:31.479071+02:00",
      "extraction_confidence": 1.0,
      "is_new": false,
      "is_booked_out": false,
      "sponsored": false,
      "editorial_tip": null,
      "source_label": "Stadt Ludwigsburg",
      "canonical_url": "https://www.rausgucken.de/ludwigsburg/events/gymnastikgruppe-fuer-frauen-55-sucht-neue-teilnehmerinnen-2026-06-18-ludw"
    },
    {
      "id": "62c0d4f40cfc7fe1",
      "title": "Maker Zone",
      "date_start": "2026-06-18",
      "date_end": null,
      "time": "16 - 18:30 Uhr",
      "description": "In der Maker Zone können Teilnehmer ihre kreativen Ideen in lebendige Projekte verwandeln. Mit Werkzeugen und Materialien zur Verfügung steht ein Raum für Experimente und Innovation.",
      "location": "Ludwigsburg",
      "price": null,
      "age_min": null,
      "age_max": null,
      "tags": [],
      "link": "https://stabi.ludwigsburg.de/start/unsere+angebote/medienwerkstatt.html",
      "original_url": "https://stabi.ludwigsburg.de/start/unsere+angebote/medienwerkstatt.html",
      "source": "ludwigsburg_stadt",
      "city": "ludwigsburg",
      "slug": "maker-zone-2026-06-18-ludw",
      "weekdays": [
        4
      ],
      "scraped_at": "2026-06-17T02:20:31.479401+02:00",
      "extraction_confidence": 1.0,
      "is_new": false,
      "is_booked_out": false,
      "sponsored": false,
      "editorial_tip": null,
      "source_label": "Stadt Ludwigsburg",
      "canonical_url": "https://www.rausgucken.de/ludwigsburg/events/maker-zone-2026-06-18-ludw"
    },
    {
      "id": "39eadba600dad7a0",
      "title": "Maker Zone",
      "date_start": "2026-06-18",
      "date_end": null,
      "time": "16:00 - 18:30",
      "description": "In der Maker Zone bietet sich die Möglichkeit, am Freitag mit Scratch zu coden. Die Veranstaltung findet von 15:30 bis 17:30 Uhr statt und richtet sich an alle Interessierten.",
      "location": "Stadtbibliothek Ludwigsburg",
      "price": "Kostenlos",
      "age_min": null,
      "age_max": null,
      "tags": [],
      "link": "https://events-stabi.ludwigsburg.de/Veranstaltung/cmx68d62376682e2.html",
      "original_url": "https://events-stabi.ludwigsburg.de/Veranstaltung/cmx68d62376682e2.html",
      "source": "stabi",
      "city": "ludwigsburg",
      "slug": "maker-zone-2026-06-18-stab",
      "weekdays": [
        4
      ],
      "scraped_at": "2026-06-17T02:15:01.604440+02:00",
      "extraction_confidence": 1.0,
      "is_new": false,
      "is_booked_out": false,
      "sponsored": false,
      "editorial_tip": null,
      "source_label": "Stadtbibliothek Ludwigsburg",
      "canonical_url": "https://www.rausgucken.de/ludwigsburg/events/maker-zone-2026-06-18-stab"
    },
    {
      "id": "60de36689173e8b8",
      "title": "Hi.Francky - AfterWork Donnerstag",
      "date_start": "2026-06-18",
      "date_end": null,
      "time": "17 - 23 Uhr",
      "description": "In der Franck-Areal bietet Hi.Francky nach der Arbeit eine Veranstaltung an, die den Donnerstagnachmittag mit kulinarischen Genüssen und netten Gesprächen bereichert.",
      "location": "Franck-Areal",
      "price": null,
      "age_min": null,
      "age_max": null,
      "tags": [
        "Kulinarik"
      ],
      "link": "https://hi-francky.com",
      "original_url": "https://hi-francky.com",
      "source": "ludwigsburg_stadt",
      "city": "ludwigsburg",
      "slug": "hifrancky---afterwork-donnerstag-2026-06-18-ludw",
      "weekdays": [
        4
      ],
      "scraped_at": "2026-06-17T02:20:31.479522+02:00",
      "extraction_confidence": 1.0,
      "is_new": false,
      "is_booked_out": false,
      "sponsored": false,
      "editorial_tip": null,
      "source_label": "Stadt Ludwigsburg",
      "canonical_url": "https://www.rausgucken.de/ludwigsburg/events/hifrancky---afterwork-donnerstag-2026-06-18-ludw"
    },
    {
      "id": "519f839263ae598f",
      "title": "...Pistes, Pisten... von Penda Diouf",
      "date_start": "2026-06-18",
      "date_end": null,
      "time": "20 Uhr",
      "description": "In dieser Veranstaltung präsentiert Künstler Penda Diouf seine Sammlung „Pistes, Pisten...“. Durchsichtige Filme und fotografische Arbeiten leiten den Besucher in die Welt der Senegalesischen Malerei ein.",
      "location": "Franck-Areal",
      "price": null,
      "age_min": null,
      "age_max": null,
      "tags": [],
      "link": "https://bit.ly/4tWKMxw",
      "original_url": "https://bit.ly/4tWKMxw",
      "source": "ludwigsburg_stadt",
      "city": "ludwigsburg",
      "slug": "pistes-pisten-von-penda-diouf-2026-06-18-ludw",
      "weekdays": [
        4
      ],
      "scraped_at": "2026-06-17T02:20:31.479954+02:00",
      "extraction_confidence": 1.0,
      "is_new": false,
      "is_booked_out": false,
      "sponsored": false,
      "editorial_tip": null,
      "source_label": "Stadt Ludwigsburg",
      "canonical_url": "https://www.rausgucken.de/ludwigsburg/events/pistes-pisten-von-penda-diouf-2026-06-18-ludw"
    },
    {
      "id": "2c416b3f18f5f293",
      "title": "Michael Barenboim & Nasmé Ensemble",
      "date_start": "2026-06-18",
      "date_end": null,
      "time": "20:00",
      "description": "In einem einzigartigen Konzert vereint Michael Barenboim und sein Nasmé Ensemble musikalische Meisterwerke verschiedener Epochen. Als Solist, Kammermusiker und Professor vermittelt er ein tiefes Verständnis für die Kunst der Performance.",
      "location": "Residenzschloss Ludwigsburg",
      "price": null,
      "age_min": null,
      "age_max": null,
      "tags": [
        "Musik",
        "Tanz"
      ],
      "link": "https://www.schloss-ludwigsburg.de/besuchsinformation/fuehrungen-veranstaltungen/weitere-informationen-zum-ausgewaehlten-angebot/michael-barenboim-nasme-ensemble/9672/790508",
      "original_url": "https://www.schloss-ludwigsburg.de/besuchsinformation/fuehrungen-veranstaltungen/weitere-informationen-zum-ausgewaehlten-angebot/michael-barenboim-nasme-ensemble/9672/790508",
      "source": "schloss",
      "city": "ludwigsburg",
      "slug": "michael-barenboim-nasme-ensemble-2026-06-18-schl",
      "weekdays": [
        4
      ],
      "scraped_at": "2026-06-17T02:00:15.313552+02:00",
      "extraction_confidence": 1.0,
      "is_new": false,
      "is_booked_out": false,
      "sponsored": false,
      "editorial_tip": null,
      "source_label": "Residenzschloss Ludwigsburg",
      "canonical_url": "https://www.rausgucken.de/ludwigsburg/events/michael-barenboim-nasme-ensemble-2026-06-18-schl"
    },
    {
      "id": "9d77df6d7abd1d4c",
      "title": "Henker, Huren, Haderlumpen im 18. Jhndt - eine grausame Erlebnis-Tour",
      "date_start": "2026-06-18",
      "date_end": null,
      "time": "20:00 - 21:30",
      "description": "In dieser Tour durch das Strafvollzugsmuseum Ludwigsburg werden die Grausamkeiten des 18. Jahrhunderts beleuchtet, darunter der Alltag von Henkern, Huren und Haderlumpen. Ein unvergessliches Erlebnis für erwachsene Besucher.",
      "location": "Strafvollzugsmuseum Ludwigsburg",
      "price": null,
      "age_min": null,
      "age_max": null,
      "tags": [
        "Fuehrung"
      ],
      "link": "https://maerchenklang.de/heute-in-Ludwigsburg/",
      "original_url": "https://maerchenklang.de/heute-in-Ludwigsburg/",
      "source": "ludwigsburg_stadt",
      "city": "ludwigsburg",
      "slug": "henker-huren-haderlumpen-im-18-jhndt---eine-grausame-erlebnis-tour-2026-06-18-ludw",
      "weekdays": [
        4
      ],
      "scraped_at": "2026-06-17T02:20:31.480224+02:00",
      "extraction_confidence": 1.0,
      "is_new": false,
      "is_booked_out": false,
      "sponsored": false,
      "editorial_tip": null,
      "source_label": "Stadt Ludwigsburg",
      "canonical_url": "https://www.rausgucken.de/ludwigsburg/events/henker-huren-haderlumpen-im-18-jhndt---eine-grausame-erlebnis-tour-2026-06-18-ludw"
    },
    {
      "id": "ef34b94f83347d6b",
      "title": "Michael Barenboim & Nasmé Ensemble – Ludwigsburger Schlossfestspiele",
      "date_start": "2026-06-18",
      "date_end": null,
      "time": "20:00 Uhr",
      "description": "In der Ordnung des Residenzschlosses bietet das Nasmé-Ensemble und der Pianist Michael Barenboim eine künstlerische Leistung an.",
      "location": "Ordenssaal, Residenzschloss",
      "price": null,
      "age_min": null,
      "age_max": null,
      "tags": [],
      "link": "https://schlossfestspiele.de/veranstaltungen/michael-barenboim/",
      "original_url": "https://schlossfestspiele.de/veranstaltungen/michael-barenboim/",
      "source": "ludwigsburg_stadt",
      "city": "ludwigsburg",
      "slug": "michael-barenboim-nasme-ensemble-ludwigsburger-schlossfestspiele-2026-06-18-ludw",
      "weekdays": [
        4
      ],
      "scraped_at": "2026-06-17T02:20:31.480570+02:00",
      "extraction_confidence": 1.0,
      "is_new": false,
      "is_booked_out": false,
      "sponsored": false,
      "editorial_tip": null,
      "source_label": "Stadt Ludwigsburg",
      "canonical_url": "https://www.rausgucken.de/ludwigsburg/events/michael-barenboim-nasme-ensemble-ludwigsburger-schlossfestspiele-2026-06-18-ludw"
    },
    {
      "id": "b5737d7fa29056e9",
      "title": "Filmklassiker von Wim Wenders (3): Der amerikanische Freund",
      "date_start": "2026-06-18",
      "date_end": null,
      "time": "20:15 Uhr",
      "description": "In dieser Veranstaltung sehen Sie drei berühmte Filme von Wim Wenders, darunter \"Der amerikanische Freund\". Das Lichtspieltheater Luna bietet eine Auswahl klassischer Werke des Regisseurs an.",
      "location": "Luna - Lichtspieltheater",
      "price": null,
      "age_min": null,
      "age_max": null,
      "tags": [],
      "link": "https://www.kinokult.de/filme/der-amerikanische-freund.html",
      "original_url": "https://www.kinokult.de/filme/der-amerikanische-freund.html",
      "source": "ludwigsburg_stadt",
      "city": "ludwigsburg",
      "slug": "filmklassiker-von-wim-wenders-3-der-amerikanische-freund-2026-06-18-ludw",
      "weekdays": [
        4
      ],
      "scraped_at": "2026-06-17T02:20:31.480649+02:00",
      "extraction_confidence": 1.0,
      "is_new": false,
      "is_booked_out": false,
      "sponsored": false,
      "editorial_tip": null,
      "source_label": "Stadt Ludwigsburg",
      "canonical_url": "https://www.rausgucken.de/ludwigsburg/events/filmklassiker-von-wim-wenders-3-der-amerikanische-freund-2026-06-18-ludw"
    }
  ]
}