{
  "subset": "tomorrow",
  "generated_at": "2026-06-20T06:00:01.435875+02:00",
  "event_count": 3,
  "disclaimer": "Die auf rausgucken.de angezeigten Veranstaltungsinformationen werden automatisch von öffentlich zugänglichen Webseiten gesammelt. Trotz größtmöglicher Sorgfalt übernehmen wir keine Gewähr für die Richtigkeit, Vollständigkeit oder Aktualität der Daten. Bitte überprüfen Sie alle Angaben auf der jeweiligen Originalseite (siehe original_url jedes Eintrags) bevor Sie teilnehmen.",
  "events": [
    {
      "id": "bd6b13a1e69b0d62",
      "title": "Hirschlander Feuerwehrhocketse",
      "date_start": "2026-06-20",
      "date_end": "2026-06-21",
      "time": null,
      "description": "In dieser Feuerwehrhocketshow demonstrieren Angehörige der Hirschlander Feuerwehr ihre Köpfe und Techniken. Ein aufregender Abend für alle Altersgruppen mit Fokus auf Action und Freude.",
      "location": "Ditzingen",
      "price": null,
      "age_min": null,
      "age_max": null,
      "tags": [],
      "link": "https://www.ditzingen.de/freizeit-kultur/veranstaltungen?c7-item=42037566",
      "original_url": "https://www.ditzingen.de/freizeit-kultur/veranstaltungen?c7-item=42037566",
      "source": "ditzingen_stadt",
      "city": "ditzingen",
      "slug": "hirschlander-feuerwehrhocketse-2026-06-20-ditz",
      "weekdays": [
        0,
        6
      ],
      "scraped_at": "2026-06-20T02:03:18.062361+02:00",
      "extraction_confidence": 1.0,
      "is_new": false,
      "is_booked_out": false,
      "sponsored": false,
      "editorial_tip": null,
      "source_label": "Stadt Ditzingen",
      "canonical_url": "https://www.rausgucken.de/ditzingen/events/hirschlander-feuerwehrhocketse-2026-06-20-ditz"
    },
    {
      "id": "b9f8e5370a9d2263",
      "title": "Vernissage und Ausstellung Kunst mit Kindern",
      "date_start": "2026-06-20",
      "date_end": "2026-07-25",
      "time": null,
      "description": "In dieser Vernissage und Ausstellung lernen Kinder und Erwachsene gemeinsam verschiedene Kunsttechniken. Ein Dozent unterstützt die Teilnehmer bei der Entdeckung von kreativen Möglichkeiten.",
      "location": "Ditzingen",
      "price": null,
      "age_min": 4,
      "age_max": 12,
      "tags": [
        "Kinder",
        "Ausstellung",
        "Familie"
      ],
      "link": "https://www.ditzingen.de/freizeit-kultur/veranstaltungen?c7-item=42660181",
      "original_url": "https://www.ditzingen.de/freizeit-kultur/veranstaltungen?c7-item=42660181",
      "source": "ditzingen_stadt",
      "city": "ditzingen",
      "slug": "vernissage-und-ausstellung-kunst-mit-kindern-2026-06-20-ditz",
      "weekdays": [
        0,
        1,
        2,
        3,
        4,
        5,
        6
      ],
      "scraped_at": "2026-06-20T02:03:18.062426+02:00",
      "extraction_confidence": 1.0,
      "is_new": false,
      "is_booked_out": false,
      "sponsored": false,
      "editorial_tip": null,
      "source_label": "Stadt Ditzingen",
      "canonical_url": "https://www.rausgucken.de/ditzingen/events/vernissage-und-ausstellung-kunst-mit-kindern-2026-06-20-ditz"
    },
    {
      "id": "0f0f0a386c20e5a4",
      "title": "Hirschlander Flöhe - privater Stadtteilflohmarkt",
      "date_start": "2026-06-21",
      "date_end": null,
      "time": "10:00 – 16:00 Uhr",
      "description": "Ein privater Flehemarkt im Stadtteil Hirschlander bietet eine ausgewählte Auswahl an Second-Hand-Gütern. Besuchern stehen geordnete Standorte und eine ruhige Atmosphäre zur Verfügung.",
      "location": "Ditzingen",
      "price": null,
      "age_min": null,
      "age_max": null,
      "tags": [],
      "link": "https://www.ditzingen.de/freizeit-kultur/veranstaltungen?c7-item=38944075",
      "original_url": "https://www.ditzingen.de/freizeit-kultur/veranstaltungen?c7-item=38944075",
      "source": "ditzingen_stadt",
      "city": "ditzingen",
      "slug": "hirschlander-floehe---privater-stadtteilflohmarkt-2026-06-21-ditz",
      "weekdays": [
        0
      ],
      "scraped_at": "2026-06-20T02:03:18.062295+02:00",
      "extraction_confidence": 1.0,
      "is_new": false,
      "is_booked_out": false,
      "sponsored": false,
      "editorial_tip": null,
      "source_label": "Stadt Ditzingen",
      "canonical_url": "https://www.rausgucken.de/ditzingen/events/hirschlander-floehe---privater-stadtteilflohmarkt-2026-06-21-ditz"
    }
  ]
}