{
  "subset": "kostenlos",
  "generated_at": "2026-07-19T09:37:26.348253+02:00",
  "event_count": 50,
  "disclaimer": "Die auf rausgucken.de angezeigten Veranstaltungsinformationen werden automatisch von öffentlich zugänglichen Webseiten gesammelt. Trotz größtmöglicher Sorgfalt übernehmen wir keine Gewähr für die Richtigkeit, Vollständigkeit oder Aktualität der Daten. Bitte überprüfen Sie alle Angaben auf der jeweiligen Originalseite (siehe original_url jedes Eintrags) bevor Sie teilnehmen.",
  "events": [
    {
      "id": "42c442cee5a6873a",
      "title": "Seniorennachmittag",
      "date_start": "2026-07-23",
      "date_end": null,
      "time": null,
      "description": null,
      "location": "Kath. Gemeindesaal",
      "price": null,
      "age_min": null,
      "age_max": null,
      "tags": [],
      "link": "https://www.sersheim.de/site/Sersheim-Layout-2022/node/20086682/zmdetail_523255057806/Seniorennachmittag.html?nodeID=523255057806",
      "original_url": "https://www.sersheim.de/site/Sersheim-Layout-2022/node/20086682/zmdetail_523255057806/Seniorennachmittag.html?nodeID=523255057806",
      "source": "sersheim_gemeinde",
      "city": "sersheim",
      "slug": "seniorennachmittag-2026-07-23-sers",
      "weekdays": [
        4
      ],
      "scraped_at": "2026-07-19T02:10:06.474376+02:00",
      "extraction_confidence": 0.75,
      "is_new": true,
      "is_booked_out": false,
      "sponsored": false,
      "editorial_tip": null,
      "source_label": "Gemeinde Sersheim",
      "canonical_url": "https://www.rausgucken.de/sersheim/events/seniorennachmittag-2026-07-23-sers"
    },
    {
      "id": "66b9b8117ea6d511",
      "title": "Gemeinderatssitzung",
      "date_start": "2026-07-24",
      "date_end": null,
      "time": null,
      "description": null,
      "location": "Ratsaal im Rathaus",
      "price": null,
      "age_min": null,
      "age_max": null,
      "tags": [],
      "link": "https://www.sersheim.de/site/Sersheim-Layout-2022/node/20086682/zmdetail_523254540208/Gemeinderatssitzung.html?nodeID=523254540208",
      "original_url": "https://www.sersheim.de/site/Sersheim-Layout-2022/node/20086682/zmdetail_523254540208/Gemeinderatssitzung.html?nodeID=523254540208",
      "source": "sersheim_gemeinde",
      "city": "sersheim",
      "slug": "gemeinderatssitzung-2026-07-24-sers",
      "weekdays": [
        5
      ],
      "scraped_at": "2026-07-19T02:10:06.474401+02:00",
      "extraction_confidence": 0.75,
      "is_new": false,
      "is_booked_out": false,
      "sponsored": false,
      "editorial_tip": null,
      "source_label": "Gemeinde Sersheim",
      "canonical_url": "https://www.rausgucken.de/sersheim/events/gemeinderatssitzung-2026-07-24-sers"
    },
    {
      "id": "c41bb9d298c09461",
      "title": "Vorlesung",
      "date_start": "2026-07-24",
      "date_end": null,
      "time": null,
      "description": null,
      "location": "VeranstaltungsortBürgersaal",
      "price": null,
      "age_min": null,
      "age_max": null,
      "tags": [],
      "link": "https://www.sersheim.de/site/Sersheim-Layout-2022/node/20086682/zmdetail_523254542402/Vorlesenachmittag.html?nodeID=523254542402",
      "original_url": "https://www.sersheim.de/site/Sersheim-Layout-2022/node/20086682/zmdetail_523254542402/Vorlesenachmittag.html?nodeID=523254542402",
      "source": "sersheim_gemeinde",
      "city": "sersheim",
      "slug": "vorlesung-2026-07-24-sers",
      "weekdays": [
        5
      ],
      "scraped_at": "2026-07-19T02:10:06.474414+02:00",
      "extraction_confidence": 0.65,
      "is_new": false,
      "is_booked_out": false,
      "sponsored": false,
      "editorial_tip": null,
      "source_label": "Gemeinde Sersheim",
      "canonical_url": "https://www.rausgucken.de/sersheim/events/vorlesung-2026-07-24-sers"
    },
    {
      "id": "2bf21004c6db3c44",
      "title": "Helfertreffen",
      "date_start": "2026-07-25",
      "date_end": null,
      "time": null,
      "description": null,
      "location": "Schützenhaus",
      "price": null,
      "age_min": null,
      "age_max": null,
      "tags": [],
      "link": "https://www.sersheim.de/site/Sersheim-Layout-2022/node/20086682/zmdetail_523254542502/Helfertreffen.html?nodeID=523254542502",
      "original_url": "https://www.sersheim.de/site/Sersheim-Layout-2022/node/20086682/zmdetail_523254542502/Helfertreffen.html?nodeID=523254542502",
      "source": "sersheim_gemeinde",
      "city": "sersheim",
      "slug": "helfertreffen-2026-07-25-sers",
      "weekdays": [
        6
      ],
      "scraped_at": "2026-07-19T02:10:06.474418+02:00",
      "extraction_confidence": 0.75,
      "is_new": false,
      "is_booked_out": false,
      "sponsored": false,
      "editorial_tip": null,
      "source_label": "Gemeinde Sersheim",
      "canonical_url": "https://www.rausgucken.de/sersheim/events/helfertreffen-2026-07-25-sers"
    },
    {
      "id": "905142d3faf6aca8",
      "title": "Gottesdienst mit Waldheim-Aussendung",
      "date_start": "2026-08-02",
      "date_end": null,
      "time": null,
      "description": null,
      "location": "Evang. Kirche",
      "price": null,
      "age_min": null,
      "age_max": null,
      "tags": [],
      "link": "https://www.sersheim.de/site/Sersheim-Layout-2022/node/20086682/zmdetail_523254542652/GottesdienstmitWaldheimAussendung.html?nodeID=523254542652",
      "original_url": "https://www.sersheim.de/site/Sersheim-Layout-2022/node/20086682/zmdetail_523254542652/GottesdienstmitWaldheimAussendung.html?nodeID=523254542652",
      "source": "sersheim_gemeinde",
      "city": "sersheim",
      "slug": "gottesdienst-mit-waldheim-aussendung-2026-08-02-sers",
      "weekdays": [
        0
      ],
      "scraped_at": "2026-07-19T02:10:06.474424+02:00",
      "extraction_confidence": 0.65,
      "is_new": false,
      "is_booked_out": false,
      "sponsored": false,
      "editorial_tip": null,
      "source_label": "Gemeinde Sersheim",
      "canonical_url": "https://www.rausgucken.de/sersheim/events/gottesdienst-mit-waldheim-aussendung-2026-08-02-sers"
    },
    {
      "id": "13791e88a69c9666",
      "title": "Whiskytasting: Schottische Whiskys",
      "date_start": "2026-08-29",
      "date_end": null,
      "time": null,
      "description": null,
      "location": "VeranstaltungsortFessler Mühle",
      "price": null,
      "age_min": null,
      "age_max": null,
      "tags": [],
      "link": "https://www.sersheim.de/site/Sersheim-Layout-2022/node/20086682/zmdetail_523254542802/WhiskytastingSchottischeWhiskys.html?nodeID=523254542802",
      "original_url": "https://www.sersheim.de/site/Sersheim-Layout-2022/node/20086682/zmdetail_523254542802/WhiskytastingSchottischeWhiskys.html?nodeID=523254542802",
      "source": "sersheim_gemeinde",
      "city": "sersheim",
      "slug": "whiskytasting-schottische-whiskys-2026-08-29-sers",
      "weekdays": [
        6
      ],
      "scraped_at": "2026-07-19T02:10:06.474432+02:00",
      "extraction_confidence": 0.75,
      "is_new": false,
      "is_booked_out": false,
      "sponsored": false,
      "editorial_tip": null,
      "source_label": "Gemeinde Sersheim",
      "canonical_url": "https://www.rausgucken.de/sersheim/events/whiskytasting-schottische-whiskys-2026-08-29-sers"
    },
    {
      "id": "ad1461fd26b8490a",
      "title": "Whisky-Wein Wanderung",
      "date_start": "2026-09-05",
      "date_end": null,
      "time": "10:00 - 18:00 Uhr",
      "description": null,
      "location": "Fessler Mühle",
      "price": null,
      "age_min": null,
      "age_max": null,
      "tags": [
        "Kulinarik"
      ],
      "link": "https://www.sersheim.de/site/Sersheim-Layout-2022/node/20086682/zmdetail_523254543502/WhiskyWeinWanderung1018Uhr.html?nodeID=523254543502",
      "original_url": "https://www.sersheim.de/site/Sersheim-Layout-2022/node/20086682/zmdetail_523254543502/WhiskyWeinWanderung1018Uhr.html?nodeID=523254543502",
      "source": "sersheim_gemeinde",
      "city": "sersheim",
      "slug": "whisky-wein-wanderung-2026-09-05-sers",
      "weekdays": [
        6
      ],
      "scraped_at": "2026-07-19T02:10:06.474437+02:00",
      "extraction_confidence": 0.75,
      "is_new": false,
      "is_booked_out": false,
      "sponsored": false,
      "editorial_tip": null,
      "source_label": "Gemeinde Sersheim",
      "canonical_url": "https://www.rausgucken.de/sersheim/events/whisky-wein-wanderung-2026-09-05-sers"
    },
    {
      "id": "1ef0477ed9d16c2f",
      "title": "Senioren Cafe",
      "date_start": "2026-09-08",
      "date_end": null,
      "time": null,
      "description": null,
      "location": "Gemeindezentrum",
      "price": null,
      "age_min": null,
      "age_max": null,
      "tags": [],
      "link": "https://www.sersheim.de/site/Sersheim-Layout-2022/node/20086682/zmdetail_523254543602/SeniorenCafe.html?nodeID=523254543602",
      "original_url": "https://www.sersheim.de/site/Sersheim-Layout-2022/node/20086682/zmdetail_523254543602/SeniorenCafe.html?nodeID=523254543602",
      "source": "sersheim_gemeinde",
      "city": "sersheim",
      "slug": "senioren-cafe-2026-09-08-sers",
      "weekdays": [
        2
      ],
      "scraped_at": "2026-07-19T02:10:06.474440+02:00",
      "extraction_confidence": 0.75,
      "is_new": false,
      "is_booked_out": false,
      "sponsored": false,
      "editorial_tip": null,
      "source_label": "Gemeinde Sersheim",
      "canonical_url": "https://www.rausgucken.de/sersheim/events/senioren-cafe-2026-09-08-sers"
    },
    {
      "id": "e23a3af6cf6643fa",
      "title": "Kreidler und Moped Treffen",
      "date_start": "2026-09-13",
      "date_end": null,
      "time": null,
      "description": null,
      "location": "Schützenhaus",
      "price": null,
      "age_min": null,
      "age_max": null,
      "tags": [],
      "link": "https://www.sersheim.de/site/Sersheim-Layout-2022/node/20086682/zmdetail_523254959150/KreidlerundMopedTreffen.html?nodeID=523254959150",
      "original_url": "https://www.sersheim.de/site/Sersheim-Layout-2022/node/20086682/zmdetail_523254959150/KreidlerundMopedTreffen.html?nodeID=523254959150",
      "source": "sersheim_gemeinde",
      "city": "sersheim",
      "slug": "kreidler-und-moped-treffen-2026-09-13-sers",
      "weekdays": [
        0
      ],
      "scraped_at": "2026-07-19T02:10:06.474446+02:00",
      "extraction_confidence": 0.85,
      "is_new": false,
      "is_booked_out": false,
      "sponsored": false,
      "editorial_tip": null,
      "source_label": "Gemeinde Sersheim",
      "canonical_url": "https://www.rausgucken.de/sersheim/events/kreidler-und-moped-treffen-2026-09-13-sers"
    },
    {
      "id": "1cc6209e43009796",
      "title": "Gemeinderatssitzung",
      "date_start": "2026-09-18",
      "date_end": null,
      "time": null,
      "description": null,
      "location": "Ratsaal im Rathaus",
      "price": null,
      "age_min": null,
      "age_max": null,
      "tags": [],
      "link": "https://www.sersheim.de/site/Sersheim-Layout-2022/node/20086682/zmdetail_523254540209/Gemeinderatssitzung.html?nodeID=523254540209",
      "original_url": "https://www.sersheim.de/site/Sersheim-Layout-2022/node/20086682/zmdetail_523254540209/Gemeinderatssitzung.html?nodeID=523254540209",
      "source": "sersheim_gemeinde",
      "city": "sersheim",
      "slug": "gemeinderatssitzung-2026-09-18-sers",
      "weekdays": [
        5
      ],
      "scraped_at": "2026-07-19T02:10:06.474448+02:00",
      "extraction_confidence": 0.75,
      "is_new": false,
      "is_booked_out": false,
      "sponsored": false,
      "editorial_tip": null,
      "source_label": "Gemeinde Sersheim",
      "canonical_url": "https://www.rausgucken.de/sersheim/events/gemeinderatssitzung-2026-09-18-sers"
    },
    {
      "id": "18dd5a06273afa6c",
      "title": "Kabarett: Hillus Herzdropfa",
      "date_start": "2026-09-30",
      "date_end": null,
      "time": null,
      "description": null,
      "location": "VeranstaltungsortFessler Mühle",
      "price": null,
      "age_min": null,
      "age_max": null,
      "tags": [
        "Entertainment"
      ],
      "link": "https://www.sersheim.de/site/Sersheim-Layout-2022/node/20086682/zmdetail_523254543952/KabarettHillusHerzdropfa.html?nodeID=523254543952",
      "original_url": "https://www.sersheim.de/site/Sersheim-Layout-2022/node/20086682/zmdetail_523254543952/KabarettHillusHerzdropfa.html?nodeID=523254543952",
      "source": "sersheim_gemeinde",
      "city": "sersheim",
      "slug": "kabarett-hillus-herzdropfa-2026-09-30-sers",
      "weekdays": [
        3
      ],
      "scraped_at": "2026-07-19T02:10:06.474469+02:00",
      "extraction_confidence": 0.75,
      "is_new": false,
      "is_booked_out": false,
      "sponsored": false,
      "editorial_tip": null,
      "source_label": "Gemeinde Sersheim",
      "canonical_url": "https://www.rausgucken.de/sersheim/events/kabarett-hillus-herzdropfa-2026-09-30-sers"
    },
    {
      "id": "3f9fc277f754d9bc",
      "title": "Kabarett: Hillus Herzdropfa",
      "date_start": "2026-10-01",
      "date_end": null,
      "time": null,
      "description": null,
      "location": "VeranstaltungsortFessler Mühle",
      "price": null,
      "age_min": null,
      "age_max": null,
      "tags": [
        "Entertainment"
      ],
      "link": "https://www.sersheim.de/site/Sersheim-Layout-2022/node/20086682/zmdetail_523254544002/KabarettHillusHerzdropfa.html?nodeID=523254544002",
      "original_url": "https://www.sersheim.de/site/Sersheim-Layout-2022/node/20086682/zmdetail_523254544002/KabarettHillusHerzdropfa.html?nodeID=523254544002",
      "source": "sersheim_gemeinde",
      "city": "sersheim",
      "slug": "kabarett-hillus-herzdropfa-2026-10-01-sers",
      "weekdays": [
        4
      ],
      "scraped_at": "2026-07-19T02:10:06.474471+02:00",
      "extraction_confidence": 0.75,
      "is_new": false,
      "is_booked_out": false,
      "sponsored": false,
      "editorial_tip": null,
      "source_label": "Gemeinde Sersheim",
      "canonical_url": "https://www.rausgucken.de/sersheim/events/kabarett-hillus-herzdropfa-2026-10-01-sers"
    },
    {
      "id": "749606b48c51f6db",
      "title": "Whiskytasting: Schottische Whiskys",
      "date_start": "2026-10-02",
      "date_end": null,
      "time": null,
      "description": null,
      "location": "VeranstaltungsortFessler Mühle",
      "price": null,
      "age_min": null,
      "age_max": null,
      "tags": [],
      "link": "https://www.sersheim.de/site/Sersheim-Layout-2022/node/20086682/zmdetail_523254544052/WhiskytastingSchottischeWhiskys.html?nodeID=523254544052",
      "original_url": "https://www.sersheim.de/site/Sersheim-Layout-2022/node/20086682/zmdetail_523254544052/WhiskytastingSchottischeWhiskys.html?nodeID=523254544052",
      "source": "sersheim_gemeinde",
      "city": "sersheim",
      "slug": "whiskytasting-schottische-whiskys-2026-10-02-sers",
      "weekdays": [
        5
      ],
      "scraped_at": "2026-07-19T02:10:06.474474+02:00",
      "extraction_confidence": 0.75,
      "is_new": false,
      "is_booked_out": false,
      "sponsored": false,
      "editorial_tip": null,
      "source_label": "Gemeinde Sersheim",
      "canonical_url": "https://www.rausgucken.de/sersheim/events/whiskytasting-schottische-whiskys-2026-10-02-sers"
    },
    {
      "id": "86548260abc89288",
      "title": "Erntedankgottesdienst",
      "date_start": "2026-10-04",
      "date_end": null,
      "time": null,
      "description": null,
      "location": "Sersheim",
      "price": null,
      "age_min": null,
      "age_max": null,
      "tags": [],
      "link": "https://www.sersheim.de/site/Sersheim-Layout-2022/node/20086682/zmdetail_523254544152/Erntedankgottesdienst.html?nodeID=523254544152",
      "original_url": "https://www.sersheim.de/site/Sersheim-Layout-2022/node/20086682/zmdetail_523254544152/Erntedankgottesdienst.html?nodeID=523254544152",
      "source": "sersheim_gemeinde",
      "city": "sersheim",
      "slug": "erntedankgottesdienst-2026-10-04-sers",
      "weekdays": [
        0
      ],
      "scraped_at": "2026-07-19T02:10:06.474479+02:00",
      "extraction_confidence": 0.85,
      "is_new": false,
      "is_booked_out": false,
      "sponsored": false,
      "editorial_tip": null,
      "source_label": "Gemeinde Sersheim",
      "canonical_url": "https://www.rausgucken.de/sersheim/events/erntedankgottesdienst-2026-10-04-sers"
    },
    {
      "id": "dea8e23e0838f795",
      "title": "Gemeinderatssitzung",
      "date_start": "2026-10-09",
      "date_end": null,
      "time": null,
      "description": null,
      "location": "Ratsaal im Rathaus",
      "price": null,
      "age_min": null,
      "age_max": null,
      "tags": [],
      "link": "https://www.sersheim.de/site/Sersheim-Layout-2022/node/20086682/zmdetail_523254540210/Gemeinderatssitzung.html?nodeID=523254540210",
      "original_url": "https://www.sersheim.de/site/Sersheim-Layout-2022/node/20086682/zmdetail_523254540210/Gemeinderatssitzung.html?nodeID=523254540210",
      "source": "sersheim_gemeinde",
      "city": "sersheim",
      "slug": "gemeinderatssitzung-2026-10-09-sers",
      "weekdays": [
        5
      ],
      "scraped_at": "2026-07-19T02:10:06.474482+02:00",
      "extraction_confidence": 0.75,
      "is_new": false,
      "is_booked_out": false,
      "sponsored": false,
      "editorial_tip": null,
      "source_label": "Gemeinde Sersheim",
      "canonical_url": "https://www.rausgucken.de/sersheim/events/gemeinderatssitzung-2026-10-09-sers"
    },
    {
      "id": "8744f382d3c84492",
      "title": "Senioren Cafe",
      "date_start": "2026-10-13",
      "date_end": null,
      "time": null,
      "description": null,
      "location": "Gemeindezentrum",
      "price": null,
      "age_min": null,
      "age_max": null,
      "tags": [],
      "link": "https://www.sersheim.de/site/Sersheim-Layout-2022/node/20086682/zmdetail_523254544202/SeniorenCafe.html?nodeID=523254544202",
      "original_url": "https://www.sersheim.de/site/Sersheim-Layout-2022/node/20086682/zmdetail_523254544202/SeniorenCafe.html?nodeID=523254544202",
      "source": "sersheim_gemeinde",
      "city": "sersheim",
      "slug": "senioren-cafe-2026-10-13-sers",
      "weekdays": [
        2
      ],
      "scraped_at": "2026-07-19T02:10:06.474486+02:00",
      "extraction_confidence": 0.75,
      "is_new": true,
      "is_booked_out": false,
      "sponsored": false,
      "editorial_tip": null,
      "source_label": "Gemeinde Sersheim",
      "canonical_url": "https://www.rausgucken.de/sersheim/events/senioren-cafe-2026-10-13-sers"
    },
    {
      "id": "5378416c9d4ac163",
      "title": "Kabarett: Hillus Herzdropfa",
      "date_start": "2026-10-14",
      "date_end": null,
      "time": null,
      "description": null,
      "location": "VeranstaltungsortFessler Mühle",
      "price": null,
      "age_min": null,
      "age_max": null,
      "tags": [
        "Entertainment"
      ],
      "link": "https://www.sersheim.de/site/Sersheim-Layout-2022/node/20086682/zmdetail_523254544252/KabarettHillusHerzdropfa.html?nodeID=523254544252",
      "original_url": "https://www.sersheim.de/site/Sersheim-Layout-2022/node/20086682/zmdetail_523254544252/KabarettHillusHerzdropfa.html?nodeID=523254544252",
      "source": "sersheim_gemeinde",
      "city": "sersheim",
      "slug": "kabarett-hillus-herzdropfa-2026-10-14-sers",
      "weekdays": [
        3
      ],
      "scraped_at": "2026-07-19T02:10:06.474489+02:00",
      "extraction_confidence": 0.75,
      "is_new": false,
      "is_booked_out": false,
      "sponsored": false,
      "editorial_tip": null,
      "source_label": "Gemeinde Sersheim",
      "canonical_url": "https://www.rausgucken.de/sersheim/events/kabarett-hillus-herzdropfa-2026-10-14-sers"
    },
    {
      "id": "ae25adbfd132f1cd",
      "title": "Kabarett: Hillus Herzdropfa",
      "date_start": "2026-10-15",
      "date_end": null,
      "time": null,
      "description": null,
      "location": "VeranstaltungsortFessler Mühle",
      "price": null,
      "age_min": null,
      "age_max": null,
      "tags": [
        "Entertainment"
      ],
      "link": "https://www.sersheim.de/site/Sersheim-Layout-2022/node/20086682/zmdetail_523254544302/KabarettHillusHerzdropfa.html?nodeID=523254544302",
      "original_url": "https://www.sersheim.de/site/Sersheim-Layout-2022/node/20086682/zmdetail_523254544302/KabarettHillusHerzdropfa.html?nodeID=523254544302",
      "source": "sersheim_gemeinde",
      "city": "sersheim",
      "slug": "kabarett-hillus-herzdropfa-2026-10-15-sers",
      "weekdays": [
        4
      ],
      "scraped_at": "2026-07-19T02:10:06.474491+02:00",
      "extraction_confidence": 0.75,
      "is_new": false,
      "is_booked_out": false,
      "sponsored": false,
      "editorial_tip": null,
      "source_label": "Gemeinde Sersheim",
      "canonical_url": "https://www.rausgucken.de/sersheim/events/kabarett-hillus-herzdropfa-2026-10-15-sers"
    },
    {
      "id": "f0889ec6bee619d4",
      "title": "Gemeindeabend",
      "date_start": "2026-10-16",
      "date_end": null,
      "time": null,
      "description": null,
      "location": "VeranstaltungsortEv. Gemeindezentrum",
      "price": null,
      "age_min": null,
      "age_max": null,
      "tags": [],
      "link": "https://www.sersheim.de/site/Sersheim-Layout-2022/node/20086682/zmdetail_523254544352/Gemeindeabend.html?nodeID=523254544352",
      "original_url": "https://www.sersheim.de/site/Sersheim-Layout-2022/node/20086682/zmdetail_523254544352/Gemeindeabend.html?nodeID=523254544352",
      "source": "sersheim_gemeinde",
      "city": "sersheim",
      "slug": "gemeindeabend-2026-10-16-sers",
      "weekdays": [
        5
      ],
      "scraped_at": "2026-07-19T02:10:06.474493+02:00",
      "extraction_confidence": 0.75,
      "is_new": false,
      "is_booked_out": false,
      "sponsored": false,
      "editorial_tip": null,
      "source_label": "Gemeinde Sersheim",
      "canonical_url": "https://www.rausgucken.de/sersheim/events/gemeindeabend-2026-10-16-sers"
    },
    {
      "id": "dc77de3b2edc3981",
      "title": "Whiskytasting",
      "date_start": "2026-10-23",
      "date_end": null,
      "time": null,
      "description": null,
      "location": "VeranstaltungsortFessler Mühle",
      "price": null,
      "age_min": null,
      "age_max": null,
      "tags": [],
      "link": "https://www.sersheim.de/site/Sersheim-Layout-2022/node/20086682/zmdetail_523254524002/WhiskytastingInternationaleWhiskys.html?nodeID=523254524002",
      "original_url": "https://www.sersheim.de/site/Sersheim-Layout-2022/node/20086682/zmdetail_523254524002/WhiskytastingInternationaleWhiskys.html?nodeID=523254524002",
      "source": "sersheim_gemeinde",
      "city": "sersheim",
      "slug": "whiskytasting-2026-10-23-sers",
      "weekdays": [
        5
      ],
      "scraped_at": "2026-07-19T02:10:06.474498+02:00",
      "extraction_confidence": 0.75,
      "is_new": false,
      "is_booked_out": false,
      "sponsored": false,
      "editorial_tip": null,
      "source_label": "Gemeinde Sersheim",
      "canonical_url": "https://www.rausgucken.de/sersheim/events/whiskytasting-2026-10-23-sers"
    },
    {
      "id": "e1ad7c84ecf6950a",
      "title": "Kabarett",
      "date_start": "2026-10-24",
      "date_end": null,
      "time": null,
      "description": null,
      "location": "Fessler Mühle",
      "price": null,
      "age_min": null,
      "age_max": null,
      "tags": [
        "Entertainment"
      ],
      "link": "https://www.sersheim.de/site/Sersheim-Layout-2022/node/20086682/zmdetail_523254524052/KabarettRobertoCapitoni.html?nodeID=523254524052",
      "original_url": "https://www.sersheim.de/site/Sersheim-Layout-2022/node/20086682/zmdetail_523254524052/KabarettRobertoCapitoni.html?nodeID=523254524052",
      "source": "sersheim_gemeinde",
      "city": "sersheim",
      "slug": "kabarett-2026-10-24-sers",
      "weekdays": [
        6
      ],
      "scraped_at": "2026-07-19T02:10:06.474501+02:00",
      "extraction_confidence": 0.85,
      "is_new": false,
      "is_booked_out": false,
      "sponsored": false,
      "editorial_tip": null,
      "source_label": "Gemeinde Sersheim",
      "canonical_url": "https://www.rausgucken.de/sersheim/events/kabarett-2026-10-24-sers"
    },
    {
      "id": "aac2096548a489d2",
      "title": "Kabarett: Elsbeth & Alois Gscheidle",
      "date_start": "2026-10-28",
      "date_end": null,
      "time": null,
      "description": null,
      "location": "Fessler Mühle",
      "price": null,
      "age_min": null,
      "age_max": null,
      "tags": [
        "Entertainment"
      ],
      "link": "https://www.sersheim.de/site/Sersheim-Layout-2022/node/20086682/zmdetail_523254524302/KabarettElsbethAloisGscheidle.html?nodeID=523254524302",
      "original_url": "https://www.sersheim.de/site/Sersheim-Layout-2022/node/20086682/zmdetail_523254524302/KabarettElsbethAloisGscheidle.html?nodeID=523254524302",
      "source": "sersheim_gemeinde",
      "city": "sersheim",
      "slug": "kabarett-elsbeth-alois-gscheidle-2026-10-28-sers",
      "weekdays": [
        3
      ],
      "scraped_at": "2026-07-19T02:10:06.474513+02:00",
      "extraction_confidence": 1.0,
      "is_new": false,
      "is_booked_out": false,
      "sponsored": false,
      "editorial_tip": null,
      "source_label": "Gemeinde Sersheim",
      "canonical_url": "https://www.rausgucken.de/sersheim/events/kabarett-elsbeth-alois-gscheidle-2026-10-28-sers"
    },
    {
      "id": "a6999782c85d8f93",
      "title": "Kabarett: Elsbeth & Alois Gscheidle",
      "date_start": "2026-10-29",
      "date_end": null,
      "time": null,
      "description": null,
      "location": "Fessler Mühle",
      "price": null,
      "age_min": null,
      "age_max": null,
      "tags": [
        "Entertainment"
      ],
      "link": "https://www.sersheim.de/site/Sersheim-Layout-2022/node/20086682/zmdetail_523254524402/KabarettElsbethAloisGscheidle.html?nodeID=523254524402",
      "original_url": "https://www.sersheim.de/site/Sersheim-Layout-2022/node/20086682/zmdetail_523254524402/KabarettElsbethAloisGscheidle.html?nodeID=523254524402",
      "source": "sersheim_gemeinde",
      "city": "sersheim",
      "slug": "kabarett-elsbeth-alois-gscheidle-2026-10-29-sers",
      "weekdays": [
        4
      ],
      "scraped_at": "2026-07-19T02:10:06.474515+02:00",
      "extraction_confidence": 1.0,
      "is_new": false,
      "is_booked_out": false,
      "sponsored": false,
      "editorial_tip": null,
      "source_label": "Gemeinde Sersheim",
      "canonical_url": "https://www.rausgucken.de/sersheim/events/kabarett-elsbeth-alois-gscheidle-2026-10-29-sers"
    },
    {
      "id": "d4af1b43c5cf7980",
      "title": "Kabarett: Markus Zipperle",
      "date_start": "2026-10-30",
      "date_end": null,
      "time": null,
      "description": null,
      "location": "Fessler Mühle",
      "price": null,
      "age_min": null,
      "age_max": null,
      "tags": [
        "Entertainment"
      ],
      "link": "https://www.sersheim.de/site/Sersheim-Layout-2022/node/20086682/zmdetail_523254524452/KabarettMarkusZipperle.html?nodeID=523254524452",
      "original_url": "https://www.sersheim.de/site/Sersheim-Layout-2022/node/20086682/zmdetail_523254524452/KabarettMarkusZipperle.html?nodeID=523254524452",
      "source": "sersheim_gemeinde",
      "city": "sersheim",
      "slug": "kabarett-markus-zipperle-2026-10-30-sers",
      "weekdays": [
        5
      ],
      "scraped_at": "2026-07-19T02:10:06.474521+02:00",
      "extraction_confidence": 0.75,
      "is_new": false,
      "is_booked_out": false,
      "sponsored": false,
      "editorial_tip": null,
      "source_label": "Gemeinde Sersheim",
      "canonical_url": "https://www.rausgucken.de/sersheim/events/kabarett-markus-zipperle-2026-10-30-sers"
    },
    {
      "id": "27da661115115ccc",
      "title": "Gemeinderatssitzung",
      "date_start": "2026-11-05",
      "date_end": null,
      "time": null,
      "description": null,
      "location": "Ratsaal im Rathaus",
      "price": null,
      "age_min": null,
      "age_max": null,
      "tags": [],
      "link": "https://www.sersheim.de/site/Sersheim-Layout-2022/node/20086682/zmdetail_523254540211/Gemeinderatssitzung.html?nodeID=523254540211",
      "original_url": "https://www.sersheim.de/site/Sersheim-Layout-2022/node/20086682/zmdetail_523254540211/Gemeinderatssitzung.html?nodeID=523254540211",
      "source": "sersheim_gemeinde",
      "city": "sersheim",
      "slug": "gemeinderatssitzung-2026-11-05-sers",
      "weekdays": [
        4
      ],
      "scraped_at": "2026-07-19T02:10:06.474528+02:00",
      "extraction_confidence": 0.75,
      "is_new": false,
      "is_booked_out": false,
      "sponsored": false,
      "editorial_tip": null,
      "source_label": "Gemeinde Sersheim",
      "canonical_url": "https://www.rausgucken.de/sersheim/events/gemeinderatssitzung-2026-11-05-sers"
    },
    {
      "id": "8366b5f8716890ef",
      "title": "Clubkonzert mit Wildfire",
      "date_start": "2026-11-07",
      "date_end": null,
      "time": null,
      "description": null,
      "location": "VeranstaltungsortVereinsheim",
      "price": null,
      "age_min": null,
      "age_max": null,
      "tags": [],
      "link": "https://www.sersheim.de/site/Sersheim-Layout-2022/node/20086682/zmdetail_523254524652/ClubkonzertmitWildfire.html?nodeID=523254524652",
      "original_url": "https://www.sersheim.de/site/Sersheim-Layout-2022/node/20086682/zmdetail_523254524652/ClubkonzertmitWildfire.html?nodeID=523254524652",
      "source": "sersheim_gemeinde",
      "city": "sersheim",
      "slug": "clubkonzert-mit-wildfire-2026-11-07-sers",
      "weekdays": [
        6
      ],
      "scraped_at": "2026-07-19T02:10:06.474534+02:00",
      "extraction_confidence": 0.75,
      "is_new": false,
      "is_booked_out": false,
      "sponsored": false,
      "editorial_tip": null,
      "source_label": "Gemeinde Sersheim",
      "canonical_url": "https://www.rausgucken.de/sersheim/events/clubkonzert-mit-wildfire-2026-11-07-sers"
    },
    {
      "id": "b2ce646ef766654e",
      "title": "Mitgliederversammlung",
      "date_start": "2026-11-07",
      "date_end": null,
      "time": null,
      "description": null,
      "location": "SKV-Heim",
      "price": null,
      "age_min": null,
      "age_max": null,
      "tags": [],
      "link": "https://www.sersheim.de/site/Sersheim-Layout-2022/node/20086682/zmdetail_523254524602/Mitgliederversammlung.html?nodeID=523254524602",
      "original_url": "https://www.sersheim.de/site/Sersheim-Layout-2022/node/20086682/zmdetail_523254524602/Mitgliederversammlung.html?nodeID=523254524602",
      "source": "sersheim_gemeinde",
      "city": "sersheim",
      "slug": "mitgliederversammlung-2026-11-07-sers",
      "weekdays": [
        6
      ],
      "scraped_at": "2026-07-19T02:10:06.474532+02:00",
      "extraction_confidence": 0.75,
      "is_new": true,
      "is_booked_out": false,
      "sponsored": false,
      "editorial_tip": null,
      "source_label": "Gemeinde Sersheim",
      "canonical_url": "https://www.rausgucken.de/sersheim/events/mitgliederversammlung-2026-11-07-sers"
    },
    {
      "id": "e6c5c7b8b01b8ce1",
      "title": "Gemeindeessen",
      "date_start": "2026-11-08",
      "date_end": null,
      "time": null,
      "description": null,
      "location": "Gemeindezentrum",
      "price": "Kostenlos",
      "age_min": null,
      "age_max": null,
      "tags": [],
      "link": "https://www.sersheim.de/site/Sersheim-Layout-2022/node/20086682/zmdetail_523254524702/Gemeindeessen.html?nodeID=523254524702",
      "original_url": "https://www.sersheim.de/site/Sersheim-Layout-2022/node/20086682/zmdetail_523254524702/Gemeindeessen.html?nodeID=523254524702",
      "source": "sersheim_gemeinde",
      "city": "sersheim",
      "slug": "gemeindeessen-2026-11-08-sers",
      "weekdays": [
        0
      ],
      "scraped_at": "2026-07-19T02:10:06.474536+02:00",
      "extraction_confidence": 0.85,
      "is_new": false,
      "is_booked_out": false,
      "sponsored": false,
      "editorial_tip": null,
      "source_label": "Gemeinde Sersheim",
      "canonical_url": "https://www.rausgucken.de/sersheim/events/gemeindeessen-2026-11-08-sers"
    },
    {
      "id": "016d70f716ce2473",
      "title": "Ökum. Martinsspiel und Laternenumzug",
      "date_start": "2026-11-08",
      "date_end": null,
      "time": null,
      "description": null,
      "location": "Spielplatz Talstraße und kath. Gemeindesaal",
      "price": null,
      "age_min": null,
      "age_max": null,
      "tags": [],
      "link": "https://www.sersheim.de/site/Sersheim-Layout-2022/node/20086682/zmdetail_523254524802/kumMartinsspielundLaternenumzug.html?nodeID=523254524802",
      "original_url": "https://www.sersheim.de/site/Sersheim-Layout-2022/node/20086682/zmdetail_523254524802/kumMartinsspielundLaternenumzug.html?nodeID=523254524802",
      "source": "sersheim_gemeinde",
      "city": "sersheim",
      "slug": "oekum-martinsspiel-und-laternenumzug-2026-11-08-sers",
      "weekdays": [
        0
      ],
      "scraped_at": "2026-07-19T02:10:06.474539+02:00",
      "extraction_confidence": 0.75,
      "is_new": false,
      "is_booked_out": false,
      "sponsored": false,
      "editorial_tip": null,
      "source_label": "Gemeinde Sersheim",
      "canonical_url": "https://www.rausgucken.de/sersheim/events/oekum-martinsspiel-und-laternenumzug-2026-11-08-sers"
    },
    {
      "id": "04aefa68556ebe81",
      "title": "Tag des Kinderturnens",
      "date_start": "2026-11-08",
      "date_end": null,
      "time": null,
      "description": null,
      "location": "Gymnastikhalle",
      "price": null,
      "age_min": null,
      "age_max": null,
      "tags": [],
      "link": "https://www.sersheim.de/site/Sersheim-Layout-2022/node/20086682/zmdetail_523254524902/TagdesKinderturnens.html?nodeID=523254524902",
      "original_url": "https://www.sersheim.de/site/Sersheim-Layout-2022/node/20086682/zmdetail_523254524902/TagdesKinderturnens.html?nodeID=523254524902",
      "source": "sersheim_gemeinde",
      "city": "sersheim",
      "slug": "tag-des-kinderturnens-2026-11-08-sers",
      "weekdays": [
        0
      ],
      "scraped_at": "2026-07-19T02:10:06.474544+02:00",
      "extraction_confidence": 0.75,
      "is_new": false,
      "is_booked_out": false,
      "sponsored": false,
      "editorial_tip": null,
      "source_label": "Gemeinde Sersheim",
      "canonical_url": "https://www.rausgucken.de/sersheim/events/tag-des-kinderturnens-2026-11-08-sers"
    },
    {
      "id": "b294f3ed8bbf9275",
      "title": "Gaumeisterschaften Geräteturnen",
      "date_start": "2026-11-08",
      "date_end": null,
      "time": null,
      "description": null,
      "location": "Sport-und Kulturhalle",
      "price": null,
      "age_min": null,
      "age_max": null,
      "tags": [],
      "link": "https://www.sersheim.de/site/Sersheim-Layout-2022/node/20086682/zmdetail_523254524852/GaumeisterschaftenGerteturnen.html?nodeID=523254524852",
      "original_url": "https://www.sersheim.de/site/Sersheim-Layout-2022/node/20086682/zmdetail_523254524852/GaumeisterschaftenGerteturnen.html?nodeID=523254524852",
      "source": "sersheim_gemeinde",
      "city": "sersheim",
      "slug": "gaumeisterschaften-geraeteturnen-2026-11-08-sers",
      "weekdays": [
        0
      ],
      "scraped_at": "2026-07-19T02:10:06.474546+02:00",
      "extraction_confidence": 0.75,
      "is_new": false,
      "is_booked_out": false,
      "sponsored": false,
      "editorial_tip": null,
      "source_label": "Gemeinde Sersheim",
      "canonical_url": "https://www.rausgucken.de/sersheim/events/gaumeisterschaften-geraeteturnen-2026-11-08-sers"
    },
    {
      "id": "c9ad61ca3138e46f",
      "title": "Pulse & Beats",
      "date_start": "2026-11-14",
      "date_end": null,
      "time": null,
      "description": null,
      "location": "VeranstaltungsortVereinsheim",
      "price": null,
      "age_min": null,
      "age_max": null,
      "tags": [],
      "link": "https://www.sersheim.de/site/Sersheim-Layout-2022/node/20086682/zmdetail_523254525052/PulseBeats.html?nodeID=523254525052",
      "original_url": "https://www.sersheim.de/site/Sersheim-Layout-2022/node/20086682/zmdetail_523254525052/PulseBeats.html?nodeID=523254525052",
      "source": "sersheim_gemeinde",
      "city": "sersheim",
      "slug": "pulse-beats-2026-11-14-sers",
      "weekdays": [
        6
      ],
      "scraped_at": "2026-07-19T02:10:06.474556+02:00",
      "extraction_confidence": 0.75,
      "is_new": true,
      "is_booked_out": false,
      "sponsored": false,
      "editorial_tip": null,
      "source_label": "Gemeinde Sersheim",
      "canonical_url": "https://www.rausgucken.de/sersheim/events/pulse-beats-2026-11-14-sers"
    },
    {
      "id": "40b88b54397a9cf0",
      "title": "Weihnachtsbaumfest",
      "date_start": "2026-11-20",
      "date_end": null,
      "time": null,
      "description": null,
      "location": "Schlösslesbrunnen",
      "price": null,
      "age_min": null,
      "age_max": null,
      "tags": [],
      "link": "https://www.sersheim.de/site/Sersheim-Layout-2022/node/20086682/zmdetail_523254526652/Weihnachtsbaumfest.html?nodeID=523254526652",
      "original_url": "https://www.sersheim.de/site/Sersheim-Layout-2022/node/20086682/zmdetail_523254526652/Weihnachtsbaumfest.html?nodeID=523254526652",
      "source": "sersheim_gemeinde",
      "city": "sersheim",
      "slug": "weihnachtsbaumfest-2026-11-20-sers",
      "weekdays": [
        5
      ],
      "scraped_at": "2026-07-19T02:10:06.474563+02:00",
      "extraction_confidence": 0.75,
      "is_new": true,
      "is_booked_out": false,
      "sponsored": false,
      "editorial_tip": null,
      "source_label": "Gemeinde Sersheim",
      "canonical_url": "https://www.rausgucken.de/sersheim/events/weihnachtsbaumfest-2026-11-20-sers"
    },
    {
      "id": "1774b968a19f3004",
      "title": "Modellbörse",
      "date_start": "2026-11-21",
      "date_end": null,
      "time": null,
      "description": null,
      "location": "Sport-und Kulturhalle",
      "price": null,
      "age_min": null,
      "age_max": null,
      "tags": [],
      "link": "https://www.sersheim.de/site/Sersheim-Layout-2022/node/20086682/zmdetail_523254526702/ModellbrseAufbau.html?nodeID=523254526702",
      "original_url": "https://www.sersheim.de/site/Sersheim-Layout-2022/node/20086682/zmdetail_523254526702/ModellbrseAufbau.html?nodeID=523254526702",
      "source": "sersheim_gemeinde",
      "city": "sersheim",
      "slug": "modellboerse-2026-11-21-sers",
      "weekdays": [
        6
      ],
      "scraped_at": "2026-07-19T02:10:06.474567+02:00",
      "extraction_confidence": 0.85,
      "is_new": true,
      "is_booked_out": false,
      "sponsored": false,
      "editorial_tip": null,
      "source_label": "Gemeinde Sersheim",
      "canonical_url": "https://www.rausgucken.de/sersheim/events/modellboerse-2026-11-21-sers"
    },
    {
      "id": "764871999fe73dcb",
      "title": "Modellbörse",
      "date_start": "2026-11-22",
      "date_end": null,
      "time": null,
      "description": null,
      "location": "Sport-und Kulturhalle",
      "price": null,
      "age_min": null,
      "age_max": null,
      "tags": [],
      "link": "https://www.sersheim.de/site/Sersheim-Layout-2022/node/20086682/zmdetail_523254526752/Modellbrse.html?nodeID=523254526752",
      "original_url": "https://www.sersheim.de/site/Sersheim-Layout-2022/node/20086682/zmdetail_523254526752/Modellbrse.html?nodeID=523254526752",
      "source": "sersheim_gemeinde",
      "city": "sersheim",
      "slug": "modellboerse-2026-11-22-sers",
      "weekdays": [
        0
      ],
      "scraped_at": "2026-07-19T02:10:06.474573+02:00",
      "extraction_confidence": 0.85,
      "is_new": true,
      "is_booked_out": false,
      "sponsored": false,
      "editorial_tip": null,
      "source_label": "Gemeinde Sersheim",
      "canonical_url": "https://www.rausgucken.de/sersheim/events/modellboerse-2026-11-22-sers"
    },
    {
      "id": "40bcf5b8f527116c",
      "title": "Kabarett: Hillus Herzdropfa",
      "date_start": "2026-11-25",
      "date_end": null,
      "time": null,
      "description": null,
      "location": "Fessler Mühle",
      "price": null,
      "age_min": null,
      "age_max": null,
      "tags": [
        "Entertainment"
      ],
      "link": "https://www.sersheim.de/site/Sersheim-Layout-2022/node/20086682/zmdetail_523254526852/KabarettHillusHerzdropfa.html?nodeID=523254526852",
      "original_url": "https://www.sersheim.de/site/Sersheim-Layout-2022/node/20086682/zmdetail_523254526852/KabarettHillusHerzdropfa.html?nodeID=523254526852",
      "source": "sersheim_gemeinde",
      "city": "sersheim",
      "slug": "kabarett-hillus-herzdropfa-2026-11-25-sers",
      "weekdays": [
        3
      ],
      "scraped_at": "2026-07-19T02:10:06.474582+02:00",
      "extraction_confidence": 0.85,
      "is_new": true,
      "is_booked_out": false,
      "sponsored": false,
      "editorial_tip": null,
      "source_label": "Gemeinde Sersheim",
      "canonical_url": "https://www.rausgucken.de/sersheim/events/kabarett-hillus-herzdropfa-2026-11-25-sers"
    },
    {
      "id": "66d2ac236d112ba7",
      "title": "Kabarett: Hillus Herzdropfa",
      "date_start": "2026-11-26",
      "date_end": null,
      "time": null,
      "description": null,
      "location": "Fessler Mühle",
      "price": null,
      "age_min": null,
      "age_max": null,
      "tags": [
        "Entertainment"
      ],
      "link": "https://www.sersheim.de/site/Sersheim-Layout-2022/node/20086682/zmdetail_523254526952/KabarettHillusHerzdropfa.html?nodeID=523254526952",
      "original_url": "https://www.sersheim.de/site/Sersheim-Layout-2022/node/20086682/zmdetail_523254526952/KabarettHillusHerzdropfa.html?nodeID=523254526952",
      "source": "sersheim_gemeinde",
      "city": "sersheim",
      "slug": "kabarett-hillus-herzdropfa-2026-11-26-sers",
      "weekdays": [
        4
      ],
      "scraped_at": "2026-07-19T02:10:06.474588+02:00",
      "extraction_confidence": 0.85,
      "is_new": true,
      "is_booked_out": false,
      "sponsored": false,
      "editorial_tip": null,
      "source_label": "Gemeinde Sersheim",
      "canonical_url": "https://www.rausgucken.de/sersheim/events/kabarett-hillus-herzdropfa-2026-11-26-sers"
    },
    {
      "id": "da4a0cf318677a09",
      "title": "Gemeinderatssitzung",
      "date_start": "2026-11-27",
      "date_end": null,
      "time": null,
      "description": null,
      "location": "Ratsaal im Rathaus",
      "price": null,
      "age_min": null,
      "age_max": null,
      "tags": [],
      "link": "https://www.sersheim.de/site/Sersheim-Layout-2022/node/20086682/zmdetail_523254540212/Gemeinderatssitzung.html?nodeID=523254540212",
      "original_url": "https://www.sersheim.de/site/Sersheim-Layout-2022/node/20086682/zmdetail_523254540212/Gemeinderatssitzung.html?nodeID=523254540212",
      "source": "sersheim_gemeinde",
      "city": "sersheim",
      "slug": "gemeinderatssitzung-2026-11-27-sers",
      "weekdays": [
        5
      ],
      "scraped_at": "2026-07-19T02:10:06.474596+02:00",
      "extraction_confidence": 0.75,
      "is_new": true,
      "is_booked_out": false,
      "sponsored": false,
      "editorial_tip": null,
      "source_label": "Gemeinde Sersheim",
      "canonical_url": "https://www.rausgucken.de/sersheim/events/gemeinderatssitzung-2026-11-27-sers"
    },
    {
      "id": "7b08e958dfb4e436",
      "title": "Whiskytasting",
      "date_start": "2026-11-27",
      "date_end": null,
      "time": null,
      "description": "In diesem Whiskytasting können Sie die Hauseigenen Mettermalt Whiskys probieren. Experten begleiten den Genuss mit Erklärungen und Anekdoten.",
      "location": "Fessler Mühle",
      "price": null,
      "age_min": null,
      "age_max": null,
      "tags": [],
      "link": "https://www.sersheim.de/site/Sersheim-Layout-2022/node/20086682/zmdetail_523254525552/WhiskytastingHauseigeneMettermaltWhiskys.html?nodeID=523254525552",
      "original_url": "https://www.sersheim.de/site/Sersheim-Layout-2022/node/20086682/zmdetail_523254525552/WhiskytastingHauseigeneMettermaltWhiskys.html?nodeID=523254525552",
      "source": "sersheim_gemeinde",
      "city": "sersheim",
      "slug": "whiskytasting-2026-11-27-sers",
      "weekdays": [
        5
      ],
      "scraped_at": "2026-07-19T02:10:06.474599+02:00",
      "extraction_confidence": 0.85,
      "is_new": true,
      "is_booked_out": false,
      "sponsored": false,
      "editorial_tip": null,
      "source_label": "Gemeinde Sersheim",
      "canonical_url": "https://www.rausgucken.de/sersheim/events/whiskytasting-2026-11-27-sers"
    },
    {
      "id": "35e68674204be829",
      "title": "Adventskonzert",
      "date_start": "2026-11-28",
      "date_end": null,
      "time": null,
      "description": null,
      "location": "Sport-und Kulturhalle",
      "price": null,
      "age_min": null,
      "age_max": null,
      "tags": [],
      "link": "https://www.sersheim.de/site/Sersheim-Layout-2022/node/20086682/zmdetail_523254527252/Adventskonzert.html?nodeID=523254527252",
      "original_url": "https://www.sersheim.de/site/Sersheim-Layout-2022/node/20086682/zmdetail_523254527252/Adventskonzert.html?nodeID=523254527252",
      "source": "sersheim_gemeinde",
      "city": "sersheim",
      "slug": "adventskonzert-2026-11-28-sers",
      "weekdays": [
        6
      ],
      "scraped_at": "2026-07-19T02:10:06.474609+02:00",
      "extraction_confidence": 0.75,
      "is_new": true,
      "is_booked_out": false,
      "sponsored": false,
      "editorial_tip": null,
      "source_label": "Gemeinde Sersheim",
      "canonical_url": "https://www.rausgucken.de/sersheim/events/adventskonzert-2026-11-28-sers"
    },
    {
      "id": "0876245864fc9730",
      "title": "Kabarett: Pfefferle & Zipperle",
      "date_start": "2026-12-05",
      "date_end": null,
      "time": null,
      "description": null,
      "location": "Fessler Mühle",
      "price": null,
      "age_min": null,
      "age_max": null,
      "tags": [
        "Entertainment"
      ],
      "link": "https://www.sersheim.de/site/Sersheim-Layout-2022/node/20086682/zmdetail_523254527302/KabarettPfefferleZipperle.html?nodeID=523254527302",
      "original_url": "https://www.sersheim.de/site/Sersheim-Layout-2022/node/20086682/zmdetail_523254527302/KabarettPfefferleZipperle.html?nodeID=523254527302",
      "source": "sersheim_gemeinde",
      "city": "sersheim",
      "slug": "kabarett-pfefferle-zipperle-2026-12-05-sers",
      "weekdays": [
        6
      ],
      "scraped_at": "2026-07-19T02:10:06.474635+02:00",
      "extraction_confidence": 0.85,
      "is_new": true,
      "is_booked_out": false,
      "sponsored": false,
      "editorial_tip": null,
      "source_label": "Gemeinde Sersheim",
      "canonical_url": "https://www.rausgucken.de/sersheim/events/kabarett-pfefferle-zipperle-2026-12-05-sers"
    },
    {
      "id": "9674bc1c8b7b1300",
      "title": "Clubkonzert mit Punch'N'Chrunch",
      "date_start": "2026-12-05",
      "date_end": null,
      "time": null,
      "description": null,
      "location": "VeranstaltungsortVereinsheim",
      "price": null,
      "age_min": null,
      "age_max": null,
      "tags": [],
      "link": "https://www.sersheim.de/site/Sersheim-Layout-2022/node/20086682/zmdetail_523254525852/ClubkonzertmitPunchNChrunch.html?nodeID=523254525852",
      "original_url": "https://www.sersheim.de/site/Sersheim-Layout-2022/node/20086682/zmdetail_523254525852/ClubkonzertmitPunchNChrunch.html?nodeID=523254525852",
      "source": "sersheim_gemeinde",
      "city": "sersheim",
      "slug": "clubkonzert-mit-punchnchrunch-2026-12-05-sers",
      "weekdays": [
        6
      ],
      "scraped_at": "2026-07-19T02:10:06.474637+02:00",
      "extraction_confidence": 0.75,
      "is_new": true,
      "is_booked_out": false,
      "sponsored": false,
      "editorial_tip": null,
      "source_label": "Gemeinde Sersheim",
      "canonical_url": "https://www.rausgucken.de/sersheim/events/clubkonzert-mit-punchnchrunch-2026-12-05-sers"
    },
    {
      "id": "4a4824e8635f1695",
      "title": "Weihnachtsfeier",
      "date_start": "2026-12-05",
      "date_end": null,
      "time": null,
      "description": null,
      "location": "Sport- und Kulturhalle",
      "price": null,
      "age_min": null,
      "age_max": null,
      "tags": [],
      "link": "https://www.sersheim.de/site/Sersheim-Layout-2022/node/20086682/zmdetail_523254525902/Weihnachtsfeier.html?nodeID=523254525902",
      "original_url": "https://www.sersheim.de/site/Sersheim-Layout-2022/node/20086682/zmdetail_523254525902/Weihnachtsfeier.html?nodeID=523254525902",
      "source": "sersheim_gemeinde",
      "city": "sersheim",
      "slug": "weihnachtsfeier-2026-12-05-sers",
      "weekdays": [
        6
      ],
      "scraped_at": "2026-07-19T02:10:06.474642+02:00",
      "extraction_confidence": 0.85,
      "is_new": true,
      "is_booked_out": false,
      "sponsored": false,
      "editorial_tip": null,
      "source_label": "Gemeinde Sersheim",
      "canonical_url": "https://www.rausgucken.de/sersheim/events/weihnachtsfeier-2026-12-05-sers"
    },
    {
      "id": "6403fed01ac99e9f",
      "title": "Adventsfeier",
      "date_start": "2026-12-08",
      "date_end": null,
      "time": null,
      "description": null,
      "location": "VeranstaltungsortBlauer Saal",
      "price": null,
      "age_min": null,
      "age_max": null,
      "tags": [],
      "link": "https://www.sersheim.de/site/Sersheim-Layout-2022/node/20086682/zmdetail_523254527452/Adventsfeier.html?nodeID=523254527452",
      "original_url": "https://www.sersheim.de/site/Sersheim-Layout-2022/node/20086682/zmdetail_523254527452/Adventsfeier.html?nodeID=523254527452",
      "source": "sersheim_gemeinde",
      "city": "sersheim",
      "slug": "adventsfeier-2026-12-08-sers",
      "weekdays": [
        2
      ],
      "scraped_at": "2026-07-19T02:10:06.474649+02:00",
      "extraction_confidence": 0.85,
      "is_new": true,
      "is_booked_out": false,
      "sponsored": false,
      "editorial_tip": null,
      "source_label": "Gemeinde Sersheim",
      "canonical_url": "https://www.rausgucken.de/sersheim/events/adventsfeier-2026-12-08-sers"
    },
    {
      "id": "ee093c990b28f6d4",
      "title": "Senioren Café",
      "date_start": "2026-12-08",
      "date_end": null,
      "time": null,
      "description": null,
      "location": "Ev. Gemeindezentrum",
      "price": null,
      "age_min": null,
      "age_max": null,
      "tags": [],
      "link": "https://www.sersheim.de/site/Sersheim-Layout-2022/node/20086682/zmdetail_523254527502/SeniorenCaf.html?nodeID=523254527502",
      "original_url": "https://www.sersheim.de/site/Sersheim-Layout-2022/node/20086682/zmdetail_523254527502/SeniorenCaf.html?nodeID=523254527502",
      "source": "sersheim_gemeinde",
      "city": "sersheim",
      "slug": "senioren-cafe-2026-12-08-sers",
      "weekdays": [
        2
      ],
      "scraped_at": "2026-07-19T02:10:06.474654+02:00",
      "extraction_confidence": 0.65,
      "is_new": true,
      "is_booked_out": false,
      "sponsored": false,
      "editorial_tip": null,
      "source_label": "Gemeinde Sersheim",
      "canonical_url": "https://www.rausgucken.de/sersheim/events/senioren-cafe-2026-12-08-sers"
    },
    {
      "id": "67150d37bbd3a6ec",
      "title": "Weihnachtsfeier",
      "date_start": "2026-12-12",
      "date_end": null,
      "time": null,
      "description": null,
      "location": "Sport- und Kulturhalle",
      "price": null,
      "age_min": null,
      "age_max": null,
      "tags": [],
      "link": "https://www.sersheim.de/site/Sersheim-Layout-2022/node/20086682/zmdetail_523254527552/Weihnachtsfeier.html?nodeID=523254527552",
      "original_url": "https://www.sersheim.de/site/Sersheim-Layout-2022/node/20086682/zmdetail_523254527552/Weihnachtsfeier.html?nodeID=523254527552",
      "source": "sersheim_gemeinde",
      "city": "sersheim",
      "slug": "weihnachtsfeier-2026-12-12-sers",
      "weekdays": [
        6
      ],
      "scraped_at": "2026-07-19T02:10:06.474660+02:00",
      "extraction_confidence": 0.85,
      "is_new": true,
      "is_booked_out": false,
      "sponsored": false,
      "editorial_tip": null,
      "source_label": "Gemeinde Sersheim",
      "canonical_url": "https://www.rausgucken.de/sersheim/events/weihnachtsfeier-2026-12-12-sers"
    },
    {
      "id": "efc25358e300f826",
      "title": "Gemeinderatssitzung - Jahresabschluss",
      "date_start": "2026-12-18",
      "date_end": null,
      "time": null,
      "description": null,
      "location": "Ratsaal im Rathaus",
      "price": null,
      "age_min": null,
      "age_max": null,
      "tags": [],
      "link": "https://www.sersheim.de/site/Sersheim-Layout-2022/node/20086682/zmdetail_523254540213/GemeinderatssitzungJahresabschluss.html?nodeID=523254540213",
      "original_url": "https://www.sersheim.de/site/Sersheim-Layout-2022/node/20086682/zmdetail_523254540213/GemeinderatssitzungJahresabschluss.html?nodeID=523254540213",
      "source": "sersheim_gemeinde",
      "city": "sersheim",
      "slug": "gemeinderatssitzung---jahresabschluss-2026-12-18-sers",
      "weekdays": [
        5
      ],
      "scraped_at": "2026-07-19T02:10:06.474665+02:00",
      "extraction_confidence": 0.85,
      "is_new": true,
      "is_booked_out": false,
      "sponsored": false,
      "editorial_tip": null,
      "source_label": "Gemeinde Sersheim",
      "canonical_url": "https://www.rausgucken.de/sersheim/events/gemeinderatssitzung---jahresabschluss-2026-12-18-sers"
    },
    {
      "id": "bf9d79173316fffc",
      "title": "Weihnachtsleider",
      "date_start": "2026-12-24",
      "date_end": null,
      "time": null,
      "description": null,
      "location": "Haus am Schlösslesbrunnen",
      "price": null,
      "age_min": null,
      "age_max": null,
      "tags": [],
      "link": "https://www.sersheim.de/site/Sersheim-Layout-2022/node/20086682/zmdetail_523254527602/Weihnachtsleider.html?nodeID=523254527602",
      "original_url": "https://www.sersheim.de/site/Sersheim-Layout-2022/node/20086682/zmdetail_523254527602/Weihnachtsleider.html?nodeID=523254527602",
      "source": "sersheim_gemeinde",
      "city": "sersheim",
      "slug": "weihnachtsleider-2026-12-24-sers",
      "weekdays": [
        4
      ],
      "scraped_at": "2026-07-19T02:10:06.474669+02:00",
      "extraction_confidence": 0.75,
      "is_new": true,
      "is_booked_out": false,
      "sponsored": false,
      "editorial_tip": null,
      "source_label": "Gemeinde Sersheim",
      "canonical_url": "https://www.rausgucken.de/sersheim/events/weihnachtsleider-2026-12-24-sers"
    },
    {
      "id": "fab826813d7461d0",
      "title": "Weihnachtswanderung",
      "date_start": "2026-12-27",
      "date_end": null,
      "time": null,
      "description": null,
      "location": "Schützenhaus",
      "price": null,
      "age_min": null,
      "age_max": null,
      "tags": [],
      "link": "https://www.sersheim.de/site/Sersheim-Layout-2022/node/20086682/zmdetail_523254527652/Weihnachtswanderung.html?nodeID=523254527652",
      "original_url": "https://www.sersheim.de/site/Sersheim-Layout-2022/node/20086682/zmdetail_523254527652/Weihnachtswanderung.html?nodeID=523254527652",
      "source": "sersheim_gemeinde",
      "city": "sersheim",
      "slug": "weihnachtswanderung-2026-12-27-sers",
      "weekdays": [
        0
      ],
      "scraped_at": "2026-07-19T02:10:06.474673+02:00",
      "extraction_confidence": 0.85,
      "is_new": true,
      "is_booked_out": false,
      "sponsored": false,
      "editorial_tip": null,
      "source_label": "Gemeinde Sersheim",
      "canonical_url": "https://www.rausgucken.de/sersheim/events/weihnachtswanderung-2026-12-27-sers"
    },
    {
      "id": "cc9909f97b109682",
      "title": "Silvester-Hocketse",
      "date_start": "2026-12-31",
      "date_end": null,
      "time": null,
      "description": null,
      "location": "Geflügelhof Grau",
      "price": null,
      "age_min": null,
      "age_max": null,
      "tags": [],
      "link": "https://www.sersheim.de/site/Sersheim-Layout-2022/node/20086682/zmdetail_523254527752/SilvesterHocketse.html?nodeID=523254527752",
      "original_url": "https://www.sersheim.de/site/Sersheim-Layout-2022/node/20086682/zmdetail_523254527752/SilvesterHocketse.html?nodeID=523254527752",
      "source": "sersheim_gemeinde",
      "city": "sersheim",
      "slug": "silvester-hocketse-2026-12-31-sers",
      "weekdays": [
        4
      ],
      "scraped_at": "2026-07-19T02:10:06.474686+02:00",
      "extraction_confidence": 0.75,
      "is_new": true,
      "is_booked_out": false,
      "sponsored": false,
      "editorial_tip": null,
      "source_label": "Gemeinde Sersheim",
      "canonical_url": "https://www.rausgucken.de/sersheim/events/silvester-hocketse-2026-12-31-sers"
    }
  ]
}