{
  "subset": "today",
  "generated_at": "2026-07-04T06:07:44.906049+02:00",
  "event_count": 2,
  "disclaimer": "Die auf rausgucken.de angezeigten Veranstaltungsinformationen werden automatisch von öffentlich zugänglichen Webseiten gesammelt. Trotz größtmöglicher Sorgfalt übernehmen wir keine Gewähr für die Richtigkeit, Vollständigkeit oder Aktualität der Daten. Bitte überprüfen Sie alle Angaben auf der jeweiligen Originalseite (siehe original_url jedes Eintrags) bevor Sie teilnehmen.",
  "events": [
    {
      "id": "cd54e07cf6e6f1f4",
      "title": "Kleinhöflefest",
      "date_start": "2026-07-04",
      "date_end": null,
      "time": "12:00 - 18:00 Uhr",
      "description": "Im Stadtkern von Kleinsachsenheim öffnen sich am 4. Juli private Höfe und Gärten für Besucher. Genießen Sie kulinarische Delikatessen und entdecken Sie sehenswerte Einrichtungen. Der Ausklang findet im alten Rathaus statt.",
      "location": "Stadtkern Kleinsachsenheim - Kirchplatz",
      "price": null,
      "age_min": null,
      "age_max": null,
      "tags": [
        "Kulinarik"
      ],
      "link": "https://www.sachsenheim.de/termin/Kleinhoeflefest-event-appointment5392",
      "original_url": "https://www.sachsenheim.de/termin/Kleinhoeflefest-event-appointment5392",
      "source": "sachsenheim_kultur",
      "city": "sachsenheim",
      "slug": "kleinhoeflefest-2026-07-04-sach",
      "weekdays": [
        6
      ],
      "scraped_at": "2026-07-04T02:03:04.621211+02:00",
      "extraction_confidence": 0.85,
      "is_new": false,
      "is_booked_out": false,
      "sponsored": false,
      "editorial_tip": null,
      "source_label": "Stadt Sachsenheim – Kulturprogramm",
      "canonical_url": "https://www.rausgucken.de/sachsenheim/events/kleinhoeflefest-2026-07-04-sach"
    },
    {
      "id": "3f3e1b9e8bc62a91",
      "title": "4. Jazz & Wein Open-Air",
      "date_start": "2026-07-04",
      "date_end": null,
      "time": "19:30 - 22:00 Uhr",
      "description": "Im 4. Jazz & Wein Open-Air verbindet kulinarischer Genuss mit leidenschaftlichem Jazz. Das Kulturprogramm mit Nawlinz Lagniappe aus Frankfurt am Main und Matthias Leucht füllt den Open-Air mit dem unverwechselbaren Sound von New Orleans. Genießen Sie temperamentvolle Musik, erlesene Weine und kulinarische Delikatessen unter freiem Himmel.",
      "location": "Weinbauer Gerd Keller, Rechentshofer Straße 8, 74343 Sachsenheim",
      "price": "18 € / 22 €",
      "age_min": null,
      "age_max": null,
      "tags": [
        "Musik",
        "Kulinarik"
      ],
      "link": "https://www.sachsenheim.de/termin/4-Jazz-Wein-Open-Air-Die-Hessen-kommen-event-appointment4886",
      "original_url": "https://www.sachsenheim.de/termin/4-Jazz-Wein-Open-Air-Die-Hessen-kommen-event-appointment4886",
      "source": "sachsenheim_kultur",
      "city": "sachsenheim",
      "slug": "4-jazz-wein-open-air-2026-07-04-sach",
      "weekdays": [
        6
      ],
      "scraped_at": "2026-07-04T02:03:05.409336+02:00",
      "extraction_confidence": 1.0,
      "is_new": false,
      "is_booked_out": false,
      "sponsored": false,
      "editorial_tip": null,
      "source_label": "Stadt Sachsenheim – Kulturprogramm",
      "canonical_url": "https://www.rausgucken.de/sachsenheim/events/4-jazz-wein-open-air-2026-07-04-sach"
    }
  ]
}