{
  "subset": "today",
  "generated_at": "2026-07-15T06:00:01.605022+02:00",
  "event_count": 1,
  "disclaimer": "Die auf rausgucken.de angezeigten Veranstaltungsinformationen werden automatisch von öffentlich zugänglichen Webseiten gesammelt. Trotz größtmöglicher Sorgfalt übernehmen wir keine Gewähr für die Richtigkeit, Vollständigkeit oder Aktualität der Daten. Bitte überprüfen Sie alle Angaben auf der jeweiligen Originalseite (siehe original_url jedes Eintrags) bevor Sie teilnehmen.",
  "events": [
    {
      "id": "acb030669fe6cbba",
      "title": "Sitzung Stiftungsrat (nicht öffentlich) - Bürgerstiftung",
      "date_start": "2026-07-15",
      "date_end": null,
      "time": null,
      "description": "Die Sitzung des Stiftungsrates der Bürgerstiftung Mundelsheim findet im Bürgerhaus statt. Diese nicht öffentliche Versammlung dient der internen Betriebswirtschaft und Strategieberatung der Stiftung.",
      "location": "Bürgerhaus Mundelsheim",
      "price": null,
      "age_min": null,
      "age_max": null,
      "tags": [],
      "link": "https://www.mundelsheim.de/veranstaltungen/2787817/2026/07/15/sitzung-stiftungsrat-nicht-öffentlich-bürgerstiftung.html",
      "original_url": "https://www.mundelsheim.de/veranstaltungen/2787817/2026/07/15/sitzung-stiftungsrat-nicht-öffentlich-bürgerstiftung.html",
      "source": "mundelsheim_veranstaltungen",
      "city": "mundelsheim",
      "slug": "sitzung-stiftungsrat-nicht-oeffentlich---buergerstiftung-2026-07-15-mund",
      "weekdays": [
        3
      ],
      "scraped_at": "2026-07-14T02:08:06.420539+02:00",
      "extraction_confidence": 1.0,
      "is_new": false,
      "is_booked_out": false,
      "sponsored": false,
      "editorial_tip": null,
      "source_label": "Gemeinde Mundelsheim",
      "canonical_url": "https://www.rausgucken.de/mundelsheim/events/sitzung-stiftungsrat-nicht-oeffentlich---buergerstiftung-2026-07-15-mund"
    }
  ]
}