{
  "subset": "next-week",
  "generated_at": "2026-07-06T06:00:02.135756+02:00",
  "event_count": 3,
  "disclaimer": "Die auf rausgucken.de angezeigten Veranstaltungsinformationen werden automatisch von öffentlich zugänglichen Webseiten gesammelt. Trotz größtmöglicher Sorgfalt übernehmen wir keine Gewähr für die Richtigkeit, Vollständigkeit oder Aktualität der Daten. Bitte überprüfen Sie alle Angaben auf der jeweiligen Originalseite (siehe original_url jedes Eintrags) bevor Sie teilnehmen.",
  "events": [
    {
      "id": "b128a1f18d143609",
      "title": "Sitzung des Jugendgemeinderats",
      "date_start": "2026-07-15",
      "date_end": null,
      "time": null,
      "description": null,
      "location": null,
      "price": null,
      "age_min": null,
      "age_max": null,
      "tags": [],
      "link": "https://www.korntal-muenchingen.de/de/Aktuelles/Veranstaltungen/Veranstaltung?view=publish&item=eventDate&id=2280",
      "original_url": "https://www.korntal-muenchingen.de/de/Aktuelles/Veranstaltungen/Veranstaltung?view=publish&item=eventDate&id=2280",
      "source": "korntal_muenchingen",
      "city": "korntal-muenchingen",
      "slug": "sitzung-des-jugendgemeinderats-2026-07-15-korn",
      "weekdays": [
        3
      ],
      "scraped_at": "2026-07-05T02:13:28.145769+02:00",
      "extraction_confidence": 0.75,
      "is_new": false,
      "is_booked_out": false,
      "sponsored": false,
      "editorial_tip": null,
      "source_label": "Stadt Korntal-Münchingen",
      "canonical_url": "https://www.rausgucken.de/korntal-muenchingen/events/sitzung-des-jugendgemeinderats-2026-07-15-korn"
    },
    {
      "id": "ea9e3ead026d9b99",
      "title": "Cuentacuentos en Español",
      "date_start": "2026-07-15",
      "date_end": null,
      "time": "16:30 Uhr",
      "description": "In der Stadtbücherei Korntal lesen Sie Kinder spanische Geschichten vor. Für Kinder ab 3 Jahren geeignet, fördert das Cuentacuentos die Sprachkenntnisse und erweckt den Interesse an literarischem Erlebnis auf Spanisch.",
      "location": "Stadtbücherei Korntal",
      "price": null,
      "age_min": 3,
      "age_max": null,
      "tags": [
        "Kinder",
        "Familie"
      ],
      "link": "https://www.korntal-muenchingen.de/de/Aktuelles/Veranstaltungen/Veranstaltung?view=publish&item=eventDate&id=2303",
      "original_url": "https://www.korntal-muenchingen.de/de/Aktuelles/Veranstaltungen/Veranstaltung?view=publish&item=eventDate&id=2303",
      "source": "korntal_muenchingen",
      "city": "korntal-muenchingen",
      "slug": "cuentacuentos-en-espanol-2026-07-15-korn",
      "weekdays": [
        3
      ],
      "scraped_at": "2026-07-05T02:13:28.145851+02:00",
      "extraction_confidence": 0.85,
      "is_new": false,
      "is_booked_out": false,
      "sponsored": false,
      "editorial_tip": null,
      "source_label": "Stadt Korntal-Münchingen",
      "canonical_url": "https://www.rausgucken.de/korntal-muenchingen/events/cuentacuentos-en-espanol-2026-07-15-korn"
    },
    {
      "id": "1e0799f24c2efb7f",
      "title": "Erste Hilfe an Handy und Computer",
      "date_start": "2026-07-16",
      "date_end": null,
      "time": "16:00 - 17:00 Uhr",
      "description": "In diesem Workshop lernen Teilnehmer, Probleme an Handys und Computern selbstständig zu lösen. Experten beantworten individuelle Fragen zur Technik.",
      "location": "Bürgertreff Korntal",
      "price": null,
      "age_min": null,
      "age_max": null,
      "tags": [
        "Workshop"
      ],
      "link": "https://www.korntal-muenchingen.de/de/Aktuelles/Veranstaltungen/Veranstaltung?view=publish&item=eventDate&id=2331",
      "original_url": "https://www.korntal-muenchingen.de/de/Aktuelles/Veranstaltungen/Veranstaltung?view=publish&item=eventDate&id=2331",
      "source": "korntal_muenchingen",
      "city": "korntal-muenchingen",
      "slug": "erste-hilfe-an-handy-und-computer-2026-07-16-korn",
      "weekdays": [
        4
      ],
      "scraped_at": "2026-07-05T02:13:28.145930+02:00",
      "extraction_confidence": 1.0,
      "is_new": false,
      "is_booked_out": false,
      "sponsored": false,
      "editorial_tip": null,
      "source_label": "Stadt Korntal-Münchingen",
      "canonical_url": "https://www.rausgucken.de/korntal-muenchingen/events/erste-hilfe-an-handy-und-computer-2026-07-16-korn"
    }
  ]
}